Workbook
Name _Hlk45015439: EquivUnid!$B$2
Name _Hlk75254411: Restricciones!$D$113
Name _Hlk75254411: 'Restricciones nuevas'!#REF!
Name _Hlk75254411: 'Restricciones SDL'!#REF!
Name _Hlk75254411: Restricciones_Futuras!#REF!

Sheet LEEME
B2: En esta hoja usted encontrará información de utilidad para entender el presente archivo. El entendimiento del contenido y organización aquí presente permitirá la explotación de la información suministrada con automatismos. Esta hoja pretende ser una ayuda para la claridad de cada hoja, columna y fila con el fin de facilitar el fin anterior (que sea usada con automatismos). Por favor, tomese el tiempo de leer cuidadosamente la descripción de cada hoja.
B13: Hoja | C13: Descripción
B14: LEEME | C14: Explicación del contenido de este archivo.
B15: LimitesImport | C15: Lista de las importaciones máximas permitidas por área del SIN. La columna "ElemName" contiene los nombres de los elementos por donde se mide la importación al área. La columna "FKEYS" contiene los foreign keys de PowerFactory para cada elemento por el cual se mide la importación. El signo + o - al frente del foreign key indica la dirección del flujo de potencia con respecto al nombre del mismo. La columna "LimiteSup [MW]" indica el máximo valor permitido.
B16: Restricciones | C16: Lista detallada de las restricciones eléctricas por área y subárea. La columna "FKEYS" contiene los foreign keys de PowerFactory para cada elemento involucrado en las restricciones listadas. El signo + o - al frente del foreign key indica la dirección del flujo de potencia con respecto al nombre del mismo. La columna "Corte [MW]" indica el máximo valor permitido para la suma de todas las potencias (con sus direcciones de flujo) en cada corte.
B17: Restricciones_Futuras | C17: Lista detallada de las restricciones eléctricas por área y subárea que se espera que se materialicen en el horizonte del mediano plazo. Esto está supeditado a la entrada de proyectos, crecimiento de demanda y otros factores. Para más información, por favor, remitirse al IPOEMP vigente.
B18: ReqUnidades_Caribe2 | C18: Tabla con los requerimientos de unidades en la subárea Caribe2 (compuesta por Atlántico, Bolivar y GCM). La demanda listada debe ser medida en estas tres subáreas. Las dos últimas columnas representan la condición del número de unidades a adicionar a la base (columna con el nombre de la subárea o área). Esta condición se refiere a la importación por medio de los elementos reportados en la hoja "Info_Elems_Condiciones". Para más detalle consultar el IPOEMP vigente.
B19: ReqUnidades_GCM | C19: Tabla con los requerimientos de unidades en la subárea GCM. La demanda listada debe ser medida en esta subárea.
B20: ReqUnidades_Suroccidental | C20: Tabla con los requerimientos de unidades en el área Suroccidental. La demanda listada debe ser medida la totalidad del área.
B21: ReqUnidades_BoyacaCasanare | C21: Tabla con los requerimientos de unidades en la subárea Boyacá-Casanare. La demanda listada debe ser medida en la subárea Boyacá-Casanare, por esta razón se lista esta única subárea en dicha tabla. Para el requerimiento de Yopal se debe validar que dentro del total para el segmento de demanda, exista al menos el número de unidades requeridas entre las que están conectadas a este nodo. Para más detalle consultar el IPOEMP vigente. Nota para el admin de este doc: En Nordeste el nombre de la columna que condiciona las yopales debe ser "1. YOPALES (2,3,4 y 5)". No cambiar.
B22: ReqUnidades_NSantander | C22: Tabla con los requerimientos de unidades en la subárea Norte de Santander. La demanda listada debe ser medida en la subárea Norte de Santander, por esta razón se lista esta única subárea en dicha tabla. Para más detalle consultar el IPOEMP vigente.
B23: ReqUnidades_Antioquia | C23: Tabla con los requerimientos de unidades en el área Suroccidental. La demanda listada debe ser medida la totalidad del área. Los requerimientos se listan por las subáreas Norte y Oriente de Antioquia.
B24: ReqUnidades_Oriental | C24: Tabla con los requerimientos de unidades en el área Oriental. La demanda listada debe ser medida en la totalidad del área. Las tres últimas columnas representan la condición del número de unidades a adicionar a la base (columna con el nombre de la subárea o área). Esta condición se refiere a la importación por medio de los elementos reportados en la hoja "Info_Elems_Condiciones". Para más detalle consultar el IPOEMP vigente.
... B30: Gráficas | C30: Esta hoja contiene información de resumen de las restricciones eléctricas listadas en la hoja "Restricciones". La información contenida aquí tiene un propósito descriptivo.
B31: Para mayor información remitirse al IPOEMP vigente.

Sheet LimitesImport
A1: Area | B1: ElemName | C1: FKEYS | D1: LimiteSup [MW]
A2: Caribe | B2: Porce III – Cerromatoso 500 kV + Primavera – Cerromatoso 500 kV + Ocaña – La Loma 500 kV + Antioquia - Cerromatoso 1 y 2 500 kV | C2: "-lrtCmt3Shn15","-LrtCmtPmv51r", "-LinOcaLom512, "+LinAntCer51r","+LinAntCer52r" | D2: 2000
A3: Oriental | B3: Primavera – Bacatá 500 Kv + La Virginia – Nueva Esperanza 500 kV | C3: "-PmvBac500","+ExpLne0135" | D3: 1320
A4: Nordeste
A5: Suroccidental | B5: Heliconia - La Virginia 500 kV + La Virginia - San Carlos 500 Kv + La Virginia - Nueva Esperanza 500 Kv | C5: "+LinVirMed51r","-LrtVirSca51r","-ExpLne0135" | D5: 650
A6: Antioquia

Sheet Restricciones
A1: Area | B1: Subárea | C1: Número | D1: Restricción | E1: FKEYS | F1: Corte [MW] | G1: ESPS | H1: Escenario | I1: Recomendación operativa | J1: Proyecto de Expansión Mediano plazo | K1: Codigo | L1: Acciones de corto plazo recomendadas | M1: Generación a limitar | N1: Generación a subir | O1: Estado restricción | P1: Origen de la restricción
A2: Caribe | B2: Caribe | C2: 1 | D2: Antioquia – Cerromatoso 1 500 kV + Antioquia – Cerromatoso 2 500 kV + Porce 3 – Cerromatoso 500 kV + Primavera – Cerromatoso 500 kV + Ocaña – La Loma 500 kV | E2: "-lrtCmt3Shn15","-LrtCmtPmv51r","-LinOcaLom512","+LinAntCer51r","+LinAntCer52r" | F2: 2000 | G2: NO | H2: Alta importación de potencia del área Caribe. | I2: • Programar generación de seguridad al interior del área Caribe de manera que se cubra el límite de importación y el requerimiento del número de unidades equivalentes • Hacer un uso adecuado de taps de transformadores y compensación reactiva del área y mantener adecuados perfiles de tensión en estado normal de operación. • En caso de que no se puedan programar las unidades equivalentes mínimas requeridas, es necesario disminuir el intercambio de potencia entre el interior y el área Caribe 2 (alrededor de 100 MW por unidad), verficando en cada caso la respuesta del sistema en estado normal de operación y ante N-1 | J2: Aumenta la capacidad de importación PTRA00322 Subestación Toluviejo 220 kV PTRA00482 Circuito Cuestecitas – La Loma 500 kV PTRA00325 UPME 06 - 2017 S/E Colectora 1 500 kV y circuitos asociados PTRA05304 Nueva Toluviejo 220/110 kV PTRA01139 UPME 06-2021 Subestación Carreto 500 kV y PTRA02158 Carreto 66 kV | K2: PTRA00203, PTRA00322, PTRA00482, PTRA00325, PTRA05304, PTRA01139, | M2: No aplica | N2: Guajira, Termonorte, Tebsa, Barranquilla, Flores 1, Flores 4, Candelaria, Cartagena, Proeléctrica | O2: 3 | P2: 0
A3: Caribe | B3: Caribe | C3: 2 | D3: Antioquia – Cerromatoso 1 500 kV + Antioquia – Cerromatoso 2 500 kV + Porce 3 – Cerromatoso 500 kV + Primavera – Cerromatoso 500 kV + Ocaña – La Loma 500 kV | E3: "+lrtCmt3Shn15","+LrtCmtPmv51r","+LinOcaLom512","-LinAntCer51r","-LinAntCer52r" | F3: 2800 | G3: NO | H3: Alta exportación de potencia del área Caribe. | I3: • Limitar la generacion en Caribe | J3: Aumenta la capacidad de importación PTRA00322 Subestación Toluviejo 220 kV PTRA00482 Circuito Cuestecitas – La Loma 500 kV PTRA00325 UPME 06 - 2017 S/E Colectora 1 500 kV y circuitos asociados PTRA05304 Nueva Toluviejo 220/110 kV PTRA01139 UPME 06-2021 Subestación Carreto 500 kV y PTRA02158 Carreto 66 kV | K3: PTRA00203, PTRA00322, PTRA00482, PTRA00325, PTRA05304, PTRA01139, | M3: Guajira, Termonorte, Tebsa, Barranquilla, Flores 1, Flores 4, Candelaria, Cartagena, Proeléctrica | N3: No aplica | O3: 3 | P3: 0
A4: Caribe | B4: Caribe2 | C4: 1 | D4: Chinú – Sabana 1 + Chinú – Sabana 2 500 kV + Ocaña – La Loma 500 kV + Chinú - El Copey 500 kV + Toluviejo – Bolívar 220 kV | E4: "+LrtSabChn51r","+LrtSabchn52r","-LinOcaLom512","+LinChnCop51T", "-LinBolTvj21" | F4: 1400 | G4: NO | H4: Alta importación de potencia del área Caribe 2. | I4: • Programar generación de seguridad al interior del área Caribe de manera que se cubra el límite de importación y el número de unidades • Hacer un uso adecuado de taps de transformadores y compensación reactiva del área y mantener adecuados perfiles de tensión en estado normal de operación. • En caso de que no se puedan programar las unidades equivalentes mínimas requeridas, es necesario disminuir el intercambio de potencia entre el interior y el área Caribe 2 (alrededor de 100 MW por unidad),vericando en cada caso la respuesta del sistema en estado normal de operación y ante N-1 | J4: Aumenta la capacidad de importación PTRA00322 Subestación Toluviejo 220 kV PTRA00482 Circuito Cuestecitas – La Loma 500 kV PTRA00325 UPME 06 - 2017 S/E Colectora 1 500 kV y circuitos asociados PTRA05304 Nueva Toluviejo 220/110 kV PTRA01139 UPME 06-2021 Subestación Carreto 500 kV y PTRA02158 Carreto 66 kV | K4: PTRA00203, PTRA00322, PTRA00482, PTRA00325, PTRA05304, PTRA01139, | M4: No aplica | N4: Guajira, Termonorte, Tebsa, Barranquilla, Flores 1, Flores 4, Candelaria, Cartagena, Proeléctrica | O4: 3 | P4: 0
A5: Caribe | B5: Caribe2 | C5: 2 | D5: Chinú – Sabana 1 + Chinú – Sabana 2 500 kV + Ocaña – La Loma 500 kV + Chinú - El Copey 500 kV + Toluviejo – Bolívar 220 kV | E5: "-LrtSabChn51r","-LrtSabchn52r","+LinOcaLom512","-LinChnCop51T", "+LinBolTvj21" | F5: 2200 | G5: NO | H5: Alta exportacion de potencia del área Caribe 2. | I5: • Limitar la generacion en Caribe 2 | J5: Aumenta la capacidad de importación PTRA00322 Subestación Toluviejo 220 kV PTRA00482 Circuito Cuestecitas – La Loma 500 kV PTRA00325 UPME 06 - 2017 S/E Colectora 1 500 kV y circuitos asociados PTRA05304 Nueva Toluviejo 220/110 kV PTRA01139 UPME 06-2021 Subestación Carreto 500 kV y PTRA02158 Carreto 66 kV | K5: PTRA00203, PTRA00322, PTRA00482, PTRA00325, PTRA05304, PTRA01139, | M5: Guajira, Termonorte, Tebsa, Barranquilla, Flores 1, Flores 4, Candelaria, Cartagena, Proeléctrica | N5: No aplica | O5: 3 | P5: 0
A6: Caribe | B6: Atlántico | C6: 1 | D6: Baja tensión en nodos Atlántico 110 kV en red completa y ante N-1 | H6: Alta demanda y baja generación al interior de la subárea | I6: Si bien, la subárea no tienen requerimiento de unidades definidos, se recomienda evaluar para demanda de Caribe 2 mayor 1671 MW la pertinencia de programar unidades al interior | J6: No hay obra de expansión definida en el horizonte de Mediano Plazo. (PTRA05299: Nueva Río 220/110 kV) Mitiga pero no elimina la restricción | M6: No aplica | N6: Tebsa, Barranquilla, Flores 1, Flores 4 | O6: 3 | P6: 0
A7: Caribe | B7: Atlántico | C7: 2 | D7: Tebsa 1 220/110 kV / Tebsa 2 220/110 kV + Tebsa 5 220/110 kV | E7: "+TrfTbs2146","+TrfTbs2017","+TrfTbs215" | F7: 220 | G7: SI | H7: Alta generación en Tebsa 220 kV y Barranquilla. Baja generación en 110 kV y Flores 4 220 kV. | I7: Realizar balance de generación entre Flores y Tebsa 220 kV + Barranquilla y/o programar generación en la red de 110 kV. En caso de no ser suficiente validar la suficiencia del ESPS asociado a sobrecarga de la transformación Tebsa 220/110 kV | J7: PTRA05299: Nueva Río 220/110 kV | K7: PTRA05299 | M7: Tebsa 220 kV, Barraquilla 220kV | N7: Tebsa 110 kV, Flores 1, Flores 4 | O7: 0 | P7: 0
A8: Caribe | B8: Atlántico | C8: 3 | D8: Tebsa 2 220/110 kV / Tebsa 1 220/110 kV + Tebsa 5 220/110 kV | E8: "+TrfTbs2017","+TrfTbs2146,"+TrfTbs215" | F8: 220 | G8: SI | H8: Alta generación en Tebsa 220 kV y Barranquilla. Baja generación en 110 kV y Flores 4 220 kV. | I8: Realizar balance de generación entre Flores y Tebsa 220 kV + Barranquilla y/o programar generación en la red de 110 kV. En caso de no ser suficiente validar la suficiencia del ESPS asociado a sobrecarga de la transformación Tebsa 220/110 kV | J8: PTRA05299: Nueva Río 220/110 kV | K8: PTRA05299 | M8: Tebsa 220 kV, Barraquilla 220kV | N8: Tebsa 110 kV, Flores 1, Flores 4 | O8: 0 | P8: 0
A9: Caribe | B9: Atlántico | C9: 4 | D9: Tebsa 5 220/110 kV / Tebsa 1 220/110 kV + Tebsa 2 220/110 kV | E9: "+TrfTbs215","+TrfTbs2146,"+TrfTbs2017" | F9: 230 | G9: SI | H9: Alta generación en Tebsa 220 kV y Barranquilla. Baja generación en 110 kV y Flores 4 220 kV. | I9: Realizar balance de generación entre Flores y Tebsa 220 kV + Barranquilla y/o programar generación en la red de 110 kV. En caso de no ser suficiente validar la suficiencia del ESPS asociado a sobrecarga de la transformación Tebsa 220/110 kV | J9: PTRA05299: Nueva Río 220/110 kV | K9: PTRA05299 | M9: Tebsa 220 kV, Barraquilla 220kV | N9: Tebsa 110 kV, Flores 1, Flores 4 | O9: 0 | P9: 0
A10: Caribe | B10: Atlántico | C10: 5 | D10: Termoflores 1 220/110 kV / Flores 2 220/110 kV | E10: "+TrfFls2011","+TrfFls2012" | F10: 220 | G10: NO | H10: Alta generación en Flores 4 a nivel de 220 kV y baja generación de Flores 1 y Flores 4 a nivel de 110 kV, Tebsa y Barranquilla | I10: Realizar balance de generación entre Flores y Tebsa y/o programar generación a nivel de 110 kV. El valor del corte dependerá del escenario de operación y si la S/E Termoflores 110 kV se opera acoplada o desacoplada | J10: PTRA05299: Nueva Río 220/110 kV | K10: PTRA05299 | M10: Flores 4 220 kV | N10: Tebsa, Barranquilla, Flores 1, Flores 4 110 kV | O10: 3 | P10: 0
A11: Caribe | B11: Atlántico | C11: 6 | D11: Flores 2 220/110 kV / Termoflores 1 220/110 kV | E11: "+TrfFls2012","+TrfFls2011" | F11: 215 | G11: NO | H11: Alta generación en Flores 4 a nivel de 220 kV y baja generación de Flores 1 y Flores 4 a nivel de 110 kV, Tebsa y Barranquilla | I11: Realizar balance de generación entre Flores y Tebsa y/o programar generación a nivel de 110 kV. El valor del corte dependerá del escenario de operación y si la S/E Termoflores 110 kV se opera acoplada o desacoplada | J11: PTRA05299: Nueva Río 220/110 kV | K11: PTRA05299 | M11: Flores 4 220 kV | N11: Tebsa, Barranquilla, Flores 1, Flores 4 110 kV | O11: 3 | P11: 0
A12: Caribe | B12: Atlántico | C12: 7 | D12: Termoflores II - Oasis 110 kV / Flores 2 220/110 kV | E12: "-CI0890","+TrfFls2012" | F12: 220 | G12: NO | H12: Con Termoflores 110 kV desacoplada. Alta generación en Flores 4 y baja generación en Flores 1, Tebsa y Barranquilla | I12: Con Termoflores 110 kV desacoplada. Realizar balance de generación entre Flores 4, Tebsa y Barranquilla y/o programar generación en Flores 1. El valor del corte dependerá de la generación que se utilice para cubrirlo | J12: PTRA05299: Nueva Río 220/110 kV | K12: PTRA05299 | M12: Flores 4 | N12: Tebsa, Barranquilla, Flores 1 | O12: 3 | P12: 0
A13: Caribe | B13: Atlántico | C13: 8 | D13: Flores 2 220/110 kV / Termoflores II - Oasis 1 110 kV | E13: "+TrfFls2012","-CI0890" | F13: 200 | G13: SI | H13: Con Termoflores 110 kV desacoplada Alta generación en Flores 4 y baja en Flores 1, Tebsa y Barranquilla | I13: Con Termoflores 110 kV desacoplada. Aumentar generación en Flores 1. Disminuir en Flores IV. Aumentar en Tebsa - Barranquilla. De no ser posible controlar esta restricción con generación, verificar suficiencia ESPS sobrecargas Termoflores II – Oasis 110 kV | J13: PTRA05299: Nueva Río 220/110 kV (mitiga pero no elimina) | M13: Flores 4 | N13: Flores 1, Tebsa, Barranquilla | O13: 0 | P13: 0
A14: Caribe | B14: Atlántico | C14: 9 | D14: Termoflores - Oasis 2 110 (acople abierto) | E14: "-CI0890" | F14: 160 | G14: SI | H14: Alta generación en Flores 1 y Flores 4 con baja generación en Tebsa y Barranquilla | I14: • Balance de generación entre Flores 1 - Flores 4 y Tebsa - Barranquilla. | J14: No hay obra de expansión definida en el horizonte de Mediano Plazo. | L14: Operar acoplada la subestación Termoflores 110 kV. Recomendación al OR y UPME aumentar capacidad de CC de las subestaciones Flores, Centro, Oasis 110 kV | M14: Flores 1, Flores 4 | N14: Tebsa, Barranquilla | O14: 3 | P14: 1
A15: Caribe | B15: Atlántico | C15: 10 | D15: Termoflores - Las Flores 2 110 / Termoflores - Las Flores 1 110 kV | E15: "-CI0564,"-LinLflTfl11" | F15: 140 | G15: SI | H15: Alta generación en Flores 1 y Flores 4 con baja generación en Tebsa y Barranquilla | I15: • Balance de generación entre Flores 1 - Flores 4 y Tebsa - Barranquilla. | J15: No hay obra de expansión definida en el horizonte de Mediano Plazo. (PTRA05299: Nueva Río 220/110 kV) mitiga pero no elimina | L15: Evaluar el aumeto de capacidad de transporte de corriente del circuito | M15: Flores 1, Flores 4 | N15: Tebsa, Barranquilla | O15: 3 | P15: 0
A16: Caribe | B16: Atlántico | C16: 11 | D16: Termoflores - Las Flores 1 110 / Termoflores - Las Flores 2 110 kV | E16: "-LinLflTfl11","-CI0564 | F16: 130 | G16: SI | H16: Alta generación en Flores 1 y Flores 4 con baja generación en Tebsa y Barranquilla | I16: • Balance de generación entre Flores 1 - Flores 4 y Tebsa - Barranquilla. | J16: No hay obra de expansión definida en el horizonte de Mediano Plazo. (PTRA05299: Nueva Río 220/110 kV) mitiga pero no elimina | M16: Flores 1, Flores 4 | N16: Tebsa, Barranquilla | O16: 3 | P16: 0
A17: Caribe | B17: Atlántico | C17: 12 | D17: Tebsa - Caracoli 1 220 / Tebsa - El Rio 1 220 | E17: "-LinCrcTeb21","-LinRioTeb21" | F17: 432 | G17: NO | H17: Maximo despacho en Tebsa y Barranquilla sin Flores 1 y Flores 4. En demanda máxima. | I17: • Disminuir la impedancia de los dispositivos SSSC ubicados en las lineas Sabanalarga - Tebsa 1 y 2 220 kV. • Aumentar la impedancia de los dispositivos SSSC ubicados en las lineas Nv Barranquilla - Termoflores 1 y 2 220 kV. (Aplicar cuidando las corrientes de enganche del dispositivo). • Balance de generacion entre Flores 1 - Flores 4 y Tebsa - Barranquilla. | J17: No hay obra de expansión definida en el horizonte de Mediano Plazo. | K17: PTRA05299 | M17: Tebsa, Barranquilla | N17: Flores 1, Flores 4 | O17: 3 | P17: 0
A18: Caribe | B18: Atlántico | C18: 13 | D18: Sobrecarga Tebsa 1 220/110 kV | E18: "+TrfTbs2146" | F18: 93 | G18: NO | H18: Mínima generación en los recursos conectados en nodos de 110 kV Alta demanda al interior de Atlántico | I18: • Programar generación en la red de 110 kV. * La transformación Tebsa 220/110 kV cuenta con un ESP ante contingencia de uno de los transformadores, sin embargo, debido a desviaciones de la demanda que se han presentado en la operación en tiempo real, es necesario cuidar este corte en red completa. | J18: PTRA05299: Nueva Río 220/110 kV | K18: PTRA05299 | M18: Tebsa 220 kV, Barraquilla 220kV | N18: Tebsa 110 kV, Flores 1, Flores 4 | O18: 1 | P18: 1
A19: Caribe | B19: Atlántico | C19: 14 | D19: Sobrecarga Tebsa 2 220/110 kV | E19: "+TrfTbs2017" | F19: 93 | G19: NO | H19: Mínima generación en los recursos conectados en nodos de 110 kV Alta demanda al interior de Atlántico | I19: • Programar generación en la red de 110 kV. * La transformación Tebsa 220/110 kV cuenta con un ESP ante contingencia de uno de los transformadores, sin embargo, debido a desviaciones de la demanda que se han presentado en la operación en tiempo real, es necesario cuidar este corte en red completa. | J19: PTRA05299: Nueva Río 220/110 kV | K19: PTRA05299 | M19: Tebsa 220 kV, Barraquilla 220kV | N19: Tebsa 110 kV, Flores 1, Flores 4 | O19: 1 | P19: 1
A20: Caribe | B20: Atlántico | C20: 15 | D20: Sobrecarga Tebsa 5 220/110 kV | E20: "+TrfTbs215" | F20: 93 | G20: NO | H20: Mínima generación en los recursos conectados en nodos de 110 kV Alta demanda al interior de Atlántico | I20: • Programar generación en la red de 110 kV. * La transformación Tebsa 220/110 kV cuenta con un ESP ante contingencia de uno de los transformadores, sin embargo, debido a desviaciones de la demanda que se han presentado en la operación en tiempo real, es necesario cuidar este corte en red completa. | J20: PTRA05299: Nueva Río 220/110 kV | K20: PTRA05299 | M20: Tebsa 220 kV, Barraquilla 220kV | N20: Tebsa 110 kV, Flores 1, Flores 4 | O20: 1 | P20: 1
A21: Caribe | B21: Atlántico | C21: 16 | D21: Sabana 9 220/115 kV / Sabana 1 220/115 kV | E21: "+TrfSab9","+TrfSab1" | F21: 90 | G21: NO | H21: Mínima generación en Atlantico Alta demanda al interior de Atlántico | I21: Programar generación en la red de 110 kV. | J21: PTRA05299: Nueva Río 220/110 kV | K21: PTRA05299 | M21: No aplica | N21: Tebsa 110 kV, Flores 1, Flores 4 | O21: 3 | P21: 0
A22: Caribe | B22: Atlántico | C22: 17 | D22: Tebsa - Vte Julio 2 110 T2 / Tebsa - Vte Julio 1 110 T2 | E22: "+LinTebVte221","+LinTebVte211" | F22: 148 | G22: SI | H22: Alta demanda en Veinte Julio 110 kV | I22: Verificar suficiencia ESP LINEAS TEBSA - VTE JULIO 110 kV | J22: No hay obra de expansión definida en el horizonte de Mediano Plazo. | M22: No aplica | N22: No aplica | O22: 0 | P22: 0
A23: Caribe | B23: Atlántico | C23: 18 | D23: Tebsa - Vte Julio 1 110 T2 / Tebsa - Vte Julio 2 110 T2 | E23: "+LinTebVte211","+LinTebVte221" | F23: 148 | G23: SI | H23: Alta demanda en Veinte Julio 110 kV | I23: Verificar suficiencia ESP LINEAS TEBSA - VTE JULIO 110 kV | J23: No hay obra de expansión definida en el horizonte de Mediano Plazo. | M23: No aplica | N23: No aplica | O23: 0 | P23: 0
A24: Caribe | B24: Atlántico | C24: 19 | D24: Agotamiento capacidad de cortocircuito de Las Flores 110 kV | G24: NO | H24: En operación gran numero de unidades de generación electricamente cercanas | I24: Con recursos de generación de la subárea en línea es posible superar la capacidad de cortocircuito de estas subestaciones por lo que se deben tomar las siguientes medidas, primero la apertura de la bahía de línea en Las Flores hacia El Río 110 kV, segundo desacoplar Termoflores 110 kV, y tercero limitar el número de unidades en línea para mitigar la condición. | J24: No hay obra de expansión definida en el horizonte de Mediano Plazo. Aumento de capacidad de corto circuito de Flores 110 kV (capacidad actual 31,5 kA de ambas subestaciones) | O24: 2 | P24: 1
A25: Caribe | B25: Atlántico | C25: 20 | D25: Agotamiento capacidad de cortocircuito de Oasis 110 kV | G25: NO | H25: En operación gran numero de unidades de generación electricamente cercanas | O25: 2 | P25: 1
A26: Caribe | B26: Atlántico | C26: 21 | D26: Agotamiento capacidad de cortocircuito de Silencio 110 kV | G26: NO | H26: En operación gran numero de unidades de generación electricamente cercanas | J26: No hay obra de expansión definida en el horizonte de Mediano Plazo. | O26: 2 | P26: 1
A27: Caribe | B27: Atlántico | C27: 22 | D27: Agotamiento capacidad de cortocircuito de El Río 110 kV | G27: NO | H27: En operación gran numero de unidades de generación electricamente cercanas | J27: No hay obra de expansión definida en el horizonte de Mediano Plazo. | O27: 2 | P27: 1
A28: Caribe | B28: Atlántico | C28: 23 | D28: Agotamiento capacidad de cortocircuito de Centro 110 kV | G28: NO | H28: En operación gran numero de unidades de generación electricamente cercanas | J28: No hay obra de expansión definida en el horizonte de Mediano Plazo. | O28: 2 | P28: 1
A29: Caribe | B29: Atlántico | C29: 24 | D29: Agotamiento capacidad de cortocircuito de Tebsa 110 kV | G29: NO | H29: En operación gran numero de unidades de generación electricamente cercanas | J29: No hay obra de expansión definida en el horizonte de Mediano Plazo. | O29: 2 | P29: 1
A30: Caribe | B30: Atlántico | C30: 25 | D30: Agotamiento capacidad de cortocircuito de Termoflores 110 kV | G30: NO | H30: En operación gran numero de unidades de generación electricamente cercanas | J30: No hay obra de expansión definida en el horizonte de Mediano Plazo. | O30: 2 | P30: 1
A31: Caribe | B31: Atlántico | C31: 26 | D31: Agotamiento capacidad de cortocircuito de Nueva Magdalena 110 kV | G31: NO | H31: En operación gran numero de unidades de generación electricamente cercanas | J31: No hay obra de expansión definida en el horizonte de Mediano Plazo. | O31: 2 | P31: 1
A32: Caribe | B32: Atlántico | C32: 27 | D32: Agotamiento capacidad de cortocircuito de Unión 110 kV | G32: NO | H32: En operación gran numero de unidades de generación electricamente cercanas | J32: No hay obra de expansión definida en el horizonte de Mediano Plazo. | O32: 2 | P32: 1
A33: Caribe | B33: Atlántico | C33: 28 | D33: Agotamiento capacidad de cortocircuito de Tebsa 220 kV | G33: NO | H33: En operación gran numero de unidades de generación electricamente cercanas | I33: Limitar el número de unidades en línea de la subárea Atlántico para mitigar la condición. | J33: No hay obra de expansión definida en el horizonte de Mediano Plazo. | O33: 2 | P33: 1
A34: Caribe | B34: Atlántico | C34: 29 | D34: Agotamiento capacidad de cortocircuito de Sabanalarga 220 kV | G34: NO | H34: En operación gran numero de unidades de generación electricamente cercanas | J34: PTRA13494: Reconfiguración de la Subestación Sabanalarga 220 Kv - FPO: 2026/11/30 | K34: PTRA13494 | O34: 2 | P34: 1
A35: Caribe | B35: Atlántico | C35: 30 | D35: Agotamiento capacidad de cortocircuito de TermoFlores 220 kV | G35: NO | H35: En operación gran numero de unidades de generación electricamente cercanas | J35: No hay obra de expansión definida en el horizonte de Mediano Plazo. | O35: 2 | P35: 1
A36: Caribe | B36: Atlántico | C36: 31 | D36: Agotamiento capacidad de cortocircuito de Nv Barranquilla 220 kV | G36: NO | H36: En operación gran numero de unidades de generación electricamente cercanas | J36: No hay obra de expansión definida en el horizonte de Mediano Plazo. | O36: 2 | P36: 1
A37: Caribe | B37: Bolívar | C37: 1 | D37: Ternera - Zaragocilla 66 kV / Cartagena - Zaragocilla 66 kV | E37: "+CI0759","+ZarCar7" | F37: 64 | G37: SI | H37: Depende de la magnitud de carga en Zaragocilla 66 kV | I37: Validarse suficiencia del ESPS de sobrecarga de las líneas Ternera – Zaragocilla 66 kV y Cartagena – Zaragocilla 66 kV | J37: PTRA02446: Subestación Campestre 66 kV, mitiga pero no es suficiente | M37: No aplica | N37: No aplica | O37: 0 | P37: 0
A38: Caribe | B38: Bolívar | C38: 2 | D38: Cartagena - Zaragocilla 66 kV / Ternera - Zaragocilla 66 kV | E38: "+ZarCar7","+CI0759" | F38: 64 | G38: SI | H38: Depende de la magnitud de carga en Zaragocilla 66 kV | I38: Validarse suficiencia del ESPS de sobrecarga de las líneas Ternera – Zaragocilla 66 kV y Cartagena – Zaragocilla 66 kV | J38: PTRA02446: Subestación Campestre 66 kV, mitiga pero no es suficiente | M38: No aplica | N38: No aplica | O38: 0 | P38: 0
A39: Caribe | B39: Bolívar | C39: 3 | D39: Baja tensión en Gambote 66 kV y Sobrecarga de Ternera – Gambote 66 kV en estado normal de operación | E39: "-CI0757" | F39: 26 | G39: NO | H39: Depende de la magnitud de carga en Gambote 66 kV | I39: Operar con tensión similar en los nodos de Ternera y Bosque 66 kV, para disminuir los Mvar en tránsito. En caso de sobrecarga o baja tensión, solicitar desatención de demanda en Gambote 66 kV | J39: PTRA01139: Carreto 500 kV y circuitos asociados. PTRA02158: Carreto 66 kV y circuitos asociados. | K39: PTRA01139, PTRA02158 | L39: Identificar obras entre los OR y la UPME para eliminar la condición radial | M39: No aplica | N39: No aplica | O39: 1 | P39: 1
A40: Caribe | B40: Bolívar | C40: 4 | D40: Proelectrica - Mamonal 66 kV / Proelectrica - Membrillal 66 kV | E40: "-CI0741","-CI1238" | F40: 94 | G40: NO | H40: Maximo despacho en Proelectrica sin Termocandelaria En demanda máxima con acople 6030 en Proelectrica 66 kV cerrado. | I40: Aumentar perfil de tension en Ternera 66 kV, limitar generación en Proelectrica | J40: No hay obra de expansión definida en el horizonte de Mediano Plazo. | M40: Proeléctrica | N40: Candelaria | O40: 0 | P40: 0
A41: Caribe | B41: Bolívar | C41: 5 | D41: Termocandelaria - Ternera 1 220 kV / Termocandelaria - Ternera 2 220 kV | E41: "+LinTcdTer21","+LinTcdTer22" | F41: 318 | G41: NO | H41: Maximo Despacho en Termocandelaria y Cartagena con los SSSC en Termocandelaria en Bypass | I41: Operar con los SSSC de Termocandelaria en 3.5 ohm de reactancia inductiva, limitar generacion en Termocandelaria y Cartagena | J41: No hay obra de expansión definida en el horizonte de Mediano Plazo. | M41: Candelaria, Cartagena | N41: No aplica | O41: 3 | P41: 0
A42: Caribe | B42: Bolívar | C42: 6 | D42: Termocandelaria - Ternera 2 220 kV / Termocandelaria - Ternera 1 220 kV | E42: "+LinTcdTer22","+LinTcdTer21" | F42: 318 | G42: NO | H42: Maximo Despacho en Termocandelaria y Cartagena con los SSSC en Termocandelaria en Bypass | I42: Operar con los SSSC de Termocandelaria en 3.5 ohm de reactancia inductiva, limitar generacion en Termocandelaria y Cartagena | J42: No hay obra de expansión definida en el horizonte de Mediano Plazo. | M42: Candelaria, Cartagena | N42: No aplica | O42: 3 | P42: 0
A43: Caribe | B43: Bolívar | C43: 7 | D43: Termocandelaria - Cartagena 1 220 kV / Termocandelaria - Cartagena 2 220 kV | E43: "-LinCtgTcd21","-LinCtgTcd22" | F43: 280 | G43: NO | H43: Maximo despacho en Caribe 2 sin Cartagena con los SSSC en Termocandelaria en modo reactancia inductiva | I43: Subir la tension en Termocandelaria, poner en modo Bypass los SSSC de Termocandelaria, limitar Termocandelaria o programar generacion en Cartagena | J43: No hay obra de expansión definida en el horizonte de Mediano Plazo. | M43: Candelaria | N43: Cartagena | O43: 3 | P43: 0
A44: Caribe | B44: Bolívar | C44: 8 | D44: Termocandelaria - Cartagena 2 220 kV / Termocandelaria - Cartagena 1 220 kV | E44: "-LinCtgTcd22","-LinCtgTcd21" | F44: 280 | G44: NO | H44: Maximo despacho en Caribe 2 sin Cartagena con los SSSC en Termocandelaria en modo reactancia inductiva | I44: Subir la tension en Termocandelaria, poner en modo Bypass los SSSC de Termocandelaria, limitar Termocandelaria o programar generacion en Cartagena | J44: No hay obra de expansión definida en el horizonte de Mediano Plazo. | M44: Candelaria | N44: Cartagena | O44: 3 | P44: 0
A45: Caribe | B45: Bolívar | C45: 9 | D45: Agotamiento capacidad de cortocircuito de Bosque 66 kV | G45: NO | H45: En operación gran numero de unidades de generación electricamente cercanas | J45: No hay obra de expansión definida en el horizonte de Mediano Plazo. | O45: 2 | P45: 1
A46: Caribe | B46: Bolívar | C46: 10 | D46: Agotamiento capacidad de cortocircuito de Cartagena 220 kV | G46: NO | H46: En operación gran numero de unidades de generación electricamente cercanas | J46: No hay obra de expansión definida en el horizonte de Mediano Plazo. | O46: 2 | P46: 1
A47: Caribe | B47: Bolívar | C47: 11 | D47: Agotamiento capacidad de cortocircuito de Ternera 66 kV | G47: NO | H47: En operación gran numero de unidades de generación electricamente cercanas | J47: No hay obra de expansión definida en el horizonte de Mediano Plazo. | O47: 2 | P47: 1
A48: Caribe | B48: Córdoba-Sucre | C48: 1 | D48: Chinú - Boston 1 110 kV / Chinú - Boston 2 110 kV | E48: "-LrtBosChn2","-LinBosChn12" | F48: 105 | G48: SI | H48: Demanda media y máxima | I48: • Validar suficiencia ESPS de sobrecarga de Chinú – Boston 110 kV | J48: PTRA00322: UPME 05 - 2018 S/E Toluviejo 220 kV, LT Chinú - Toluviejo 220 kV y Toluviejo - Bolívar 220 kV PTRA05304: Nueva Toluviejo 220/110 kV | K48: PTRA00322, PTRA05304 | M48: No aplica | N48: Candelaria, Cartagena, Proeléctrica | O48: 0 | P48: 0
A49: Caribe | B49: Córdoba-Sucre | C49: 2 | D49: Chinú - Coveñas 110 kV / Chinú - Boston 110 kV | E49: "+CI0817","-LrtBosChn2" | F49: 135 | G49: SI | H49: Demanda media y máxima | I49: • Validar suficiencia ESPS de sobrecarga de Boston – Sierra Flor 110 kV, Chinú – Boston 110 kV y ESPS baja tensión en Zambrano 66 kV | J49: PTRA00322: UPME 05 - 2018 S/E Toluviejo 220 kV, LT Chinú - Toluviejo 220 kV y Toluviejo - Bolívar 220 kV PTRA05304: Nueva Toluviejo 220/110 kV | K49: PTRA00322, PTRA05304 | M49: No aplica | N49: Candelaria, Cartagena, Proeléctrica | O49: 0 | P49: 0
A50: Caribe | B50: Córdoba-Sucre | C50: 3 | D50: Chinú - Coveñas 110 kV / Boston - Sierraflor 110 kV | E50: "+CI0817","+CI0800" | F50: 150 | G50: SI | H50: Demanda media y máxima | I50: • Validar suficiencia ESPS de sobrecarga de Boston – Sierra Flor 110 kV, Chinú – Boston 110 kV y ESPS baja tensión en Zambrano y San Jacinto 66 kV | J50: PTRA00322: UPME 05 - 2018 S/E Toluviejo 220 kV, LT Chinú - Toluviejo 220 kV y Toluviejo - Bolívar 220 kV PTRA05304: Nueva Toluviejo 220/110 kV | K50: PTRA00322, PTRA05304 | M50: No aplica | N50: Candelaria, Cartagena, Proeléctrica | O50: 0 | P50: 0
A51: Caribe | B51: Córdoba-Sucre | C51: 4 | D51: Baja tensión en Mompox 110 kV | G51: NO | H51: Demanda media y máxima | I51: • Mejorar el perfil de tensión desde Chinú 110 kV (el corte esta calulado con tensión minima en Chinu de 117 kV) • De no ser suficiente o posible, deberá evaluarse el realizar desatención de demanda. | J51: No hay obra de expansión definida en el horizonte de Mediano Plazo. (PTRA00686: Compensación capacitiva Mompox 2x8 Mvar mitiga, pero no elimina la restricción) | L51: Identificar obras entre los OR y la UPME para eliminar la condición radial | M51: No aplica | N51: No aplica | O51: 1 | P51: 1
A52: Caribe | B52: Córdoba-Sucre | C52: 5 | D52: Chinú 3 500/110 kV / Chinú 1 500/110 kV + Chinú 2 500/110 kV | E52: "+TrfChn3","+TrfChn5131","+TrfChn5132" | F52: 290 | G52: SI | H52: Demanda media y máxima | I52: • Validar suficiencia del ESPS de sobrecarga transfomadores Chinú 500/110 kV | J52: No hay obra de expansión definida en el horizonte de Mediano Plazo. (PTRA00322 y PTRA05304: Nueva Toluviejo 220/110 kV y obras asociadas mitigan, pero no elimina la restricción). 4 TRF Chinu 500/110 kV elimina | M52: No aplica | N52: No aplica | O52: 0 | P52: 0
A53: Caribe | B53: Córdoba-Sucre | C53: 6 | D53: Chinú 2 500/110 kV / Chinú 1 500/110 kV + Chinú 3 500/110 kV | E53: "+TrfChn5132","+TrfChn5131","+TrfChn3" | F53: 290 | G53: SI | H53: Demanda media y máxima | I53: • Validar suficiencia del ESPS de sobrecarga transfomadores Chinú 500/110 kV | J53: No hay obra de expansión definida en el horizonte de Mediano Plazo. (PTRA00322 y PTRA05304: Nueva Toluviejo 220/110 kV y obras asociadas mitigan, pero no elimina la restricción). 4 TRF Chinu 500/110 kV elimina | M53: No aplica | N53: No aplica | O53: 0 | P53: 0
A54: Caribe | B54: Córdoba-Sucre | C54: 7 | D54: Chinú 1 500/110 kV / Chinú 3 500/110 kV + Chinú 2 500/110 kV | E54: "+TrfChn5131","+TrfChn3","+TrfChn5132" | F54: 290 | G54: SI | H54: Demanda media y máxima | I54: • Validar suficiencia del ESPS de sobrecarga transfomadores Chinú 500/110 kV | J54: No hay obra de expansión definida en el horizonte de Mediano Plazo. (PTRA00322 y PTRA05304: Nueva Toluviejo 220/110 kV y obras asociadas mitigan, pero no elimina la restricción). 4 TRF Chinu 500/110 kV elimina | M54: No aplica | N54: No aplica | O54: 0 | P54: 0
A55: Caribe | B55: Córdoba-Sucre | C55: 8 | D55: Interruptor 7020 Chinú 110 kV (Barra 1 a Barra 2) / Chinú 1 500/110 kV | E55: "+Brk05481","+TrfChn5131" | F55: 150 | G55: SI | H55: Baja generación en Urrá y al interior de Bolívar. En demanda máxima y media. | I55: • Validar suficiencia del ESPS de sobrecarga transfomadores Chinú 500/110 kV | J55: PTRA00322: UPME 05 - 2018 S/E Toluviejo 220 kV, LT Chinú - Toluviejo 220 kV y Toluviejo - Bolívar 220 kV PTRA05304: Nueva Toluviejo 220/110 kV | K55: PTRA00322, PTRA05304 | M55: No aplica | N55: No aplica | O55: 0 | P55: 0
A56: Caribe | B56: Córdoba-Sucre | C56: 9 | D56: Nueva Montería – Río Sinú 110 kV / Baja tensión en Rio Sinú 110 kV | H56: Demanda máxima y media. Baja generación en Urrá | I56: Programar generación en Urra y a través del tap de Urra 230/115 kV, buscar un perfil de tensión seguro para Urra 110 kV (comúnmente entre 117 – 118 kV) | J56: PTRA13477 Urrá - Tierralta 2 110 kV + Tierralta - Río Sinú 2 110 kV (promotor pendiente de asignación) | M56: No aplica | N56: No aplica | O56: 1 | P56: 0
A57: Caribe | B57: Córdoba-Sucre | C57: 10 | D57: Nueva Montería – Río Sinú 110 kV / Urrá - Tierra Alta 1 110 kV | E57: "+LinNMnRSn11","-CI0975 | F57: 75 | G57: SI | H57: Demanda máxima y media. | I57: • Validar suficiencia del ESPS de sobrecarga Urrá-Tierra Alta 110 kV | J57: PTRA13477 Urrá - Tierralta 2 110 kV + Tierralta - Río Sinú 2 110 kV (promotor pendiente de asignación) | M57: No aplica | N57: No aplica | O57: 0 | P57: 0
A58: Caribe | B58: Córdoba-Sucre | C58: 11 | D58: Río Sinú – Tierra Alta 110 kV / Alta tensión en Urrá 110 kV, Tierra Alta 110 kV y Nueva Monteria 110 kV | G58: NO | H58: Baja generación en Urrá y al interior de Bolívar. | I58: A través del generador Urra y el tap de Urra 230/115 kV, buscar un perfil de tensión seguro para Urra 110 kV que mitigue esta condición (comúnmente entre 117 – 118 kV). | J58: No hay obra de expansión definida en el horizonte de Mediano Plazo | M58: No aplica | N58: No aplica | O58: 3 | P58: 0
A59: Caribe | B59: Córdoba-Sucre | C59: 12 | D59: Urrá - Urabá 230 kV / Urrá - Tierra Alta 110 kV | E59: "-LinUrbUrr21","-CI0975" | F59: 240 | G59: SI | H59: Demanda máxima y media. Alta generación en Urrá | I59: Limitar la generación de Urrá | J59: No hay obra de expansión definida en el horizonte de Mediano Plazo | M59: Si aplica | N59: No aplica | O59: 0 | P59: 0
A60: Caribe | B60: Córdoba-Sucre | C60: 13 | D60: Boston - Sierra flor 110 kV / Baja tensión en Toluviejo 110 kV, El Carmen 110/66 kV, Zambrano y San jacinto 66 kV | H60: Restricción dependiente de la demanda. | I60: Validar la suficiencia del ESPS de baja tensión en Zambrano y San Jacinto 66 kV, en caso contrario evaluar pertinencia si el caso de solicitar desconexión de demanda. | J60: PTRA00322: Toluviejo 220 kV y líneas asociadas PTRA05304: Nueva Toluviejo 220/110 kV PTRA01139: Carreto 500 kV y circuitos asociados. PTRA02158: Carreto 66 kV y circuitos asociados. | K60: PTRA00322, PTRA05304, PTRA01139, PTRA02158 | M60: No aplica | N60: No aplica | O60: 3 | P60: 0
A61: Caribe | B61: Córdoba-Sucre | C61: 14 | D61: Baja tensión en nodos El Carmen, Calamar, Zambrano, San Jacinto 66 kV y El Carmen 110 kV en red completa y ante contingencia sencilla | H61: En demanda máxima y media. | I61: • Ante contingencia verificar suficiencia de los ESPS de Córdoba - Sucre (circuitos entre Chinú y Toluviejo 110 kV) y el ESPS por baja tensión en Boston 110 kV, San Jacinto 66 kV y Zambrano 66 kV | J61: PTRA00322: Toluviejo 220 kV y líneas asociadas PTRA05304: Nueva Toluviejo 220/110 kV PTRA01139: Carreto 500 kV y circuitos asociados. PTRA02158: Carreto 66 kV y circuitos asociados. | K61: PTRA00322, PTRA05304, PTRA01139, PTRA02158 | M61: No aplica | N61: No aplica | O61: 1 | P61: 0
A62: Caribe | B62: Córdoba-Sucre | C62: 15 | D62: Sobrecarga Transformador Chinú 1 500/110 kV | E62: "+TrfChn5131" | F62: 130 | G62: SI | H62: Demanda máxima | I62: El esquema de los transformadores no opera en esos valores de sobrecarga. Se recomienda gestionar la reactiva por los transformadores mediante los tapas de Chinú y Montería, para evitar/mitigar la DNA | J62: PTRA00322: UPME 05 - 2018 S/E Toluviejo 220 kV, LT Chinú - Toluviejo 220 kV y Toluviejo - Bolívar 220 kV PTRA05304: Nueva Toluviejo 220/110 kV | K62: PTRA00322, PTRA05304 | M62: No aplica | N62: No aplica | O62: 1 | P62: 1
A63: Caribe | B63: Córdoba-Sucre | C63: 16 | D63: Sobrecarga Transformador Chinú 2 500/110 kV | E63: "+TrfChn5132" | F63: 130 | G63: SI | H63: Demanda máxima | I63: El esquema de los transformadores no opera en esos valores de sobrecarga. Se recomienda gestionar la reactiva por los transformadores mediante los tapas de Chinú y Montería, para evitar/mitigar la DNA | J63: PTRA00322: UPME 05 - 2018 S/E Toluviejo 220 kV, LT Chinú - Toluviejo 220 kV y Toluviejo - Bolívar 220 kV PTRA05304: Nueva Toluviejo 220/110 kV | K63: PTRA00322, PTRA05304 | M63: No aplica | N63: No aplica | O63: 1 | P63: 1
A64: Caribe | B64: Córdoba-Sucre | C64: 17 | D64: Sobrecarga Transformador Chinú 3 500/110 kV | E64: "+TrfChn3" | F64: 130 | G64: SI | H64: Demanda máxima | I64: El esquema de los transformadores no opera en esos valores de sobrecarga. Se recomienda gestionar la reactiva por los transformadores mediante los tapas de Chinú y Montería, para evitar/mitigar la DNA | J64: PTRA00322: UPME 05 - 2018 S/E Toluviejo 220 kV, LT Chinú - Toluviejo 220 kV y Toluviejo - Bolívar 220 kV PTRA05304: Nueva Toluviejo 220/110 kV | K64: PTRA00322, PTRA05304 | M64: No aplica | N64: No aplica | O64: 1 | P64: 1
A65: Caribe | B65: Córdoba-Sucre | C65: 18 | D65: Nueva Monteria 1 230/110 kV / Nueva Monteria 2 230/110 kV | E65: "+TrfMon211,"+TrfMon212" | F65: 113 | G65: SI | H65: Demanda máxima | I65: Hacer uso del capacitor en Montería 110 kV y subir tensiones en Urra 110 kV y Chinú 110 kV para disminuir los Mvar en tránsito. | J65: Obras del refuerzo Monteria | M65: No aplica | N65: No aplica | O65: 0 | P65: 0
A66: Caribe | B66: Córdoba-Sucre | C66: 19 | D66: Nueva Monteria 2 230/110 kV / Nueva Monteria 1 230/110 kV | E66: "+TrfMon212,"+TrfMon211" | F66: 113 | G66: SI | H66: Demanda máxima | I66: Hacer uso del capacitor en Montería 110 kV y subir tensiones en Urra 110 kV y Chinú 110 kV para disminuir los Mvar en tránsito. | J66: Obras del refuerzo Monteria | M66: No aplica | N66: No aplica | O66: 0 | P66: 0
A67: Caribe | B67: Córdoba-Sucre | C67: 20 | D67: Urrá - Urabá 230 kV / baja tensión en Apartado, Nueva Colonia y Caucheras 110 kV | H67: Demanda máxima | I67: Subir tensiones en Uraba 110 kV y Chinu 220 kV | J67: Obras del refuerzo Monteria | M67: No aplica | N67: No aplica | O67: 3 | P67: 0
A68: Caribe | B68: Córdoba-Sucre | C68: 21 | D68: Sobrecarga en red completa Sincé – Magangué 110 kV | E68: "-CI0816" | F68: 73 | G68: NO | H68: Demanda máxima | I68: • Hacer uso de los capacitores en Mompox 110 kV y 34.5 kV para controlar el transporte de reactivos a través de la línea. • De no ser suficiente o posible, deberá evaluarse el realizar desatención de demanda. | J68: No hay obra de expansión definida en el horizonte de Mediano Plazo | M68: No aplica | N68: No aplica | O68: 1 | P68: 1
A69: Caribe | B69: Córdoba-Sucre | C69: 22 | D69: Agotamiento capacidad de cortocircuito de Chinú 110 kV | G69: NO | H69: En línea un alto número de recursos de generación cercanos eléctricamente | J69: No hay obra de expansión definida en el horizonte de Mediano Plazo. | O69: 2 | P69: 1
A70: Caribe | B70: GCM | C70: 1 | D70: Baja tensión en El Banco 110 kV | G70: SI | H70: Independiente del escenario. | J70: PTRA13263: UPME 02 - 2024 S/E Magangué 500 kV y líneas de transmisión asociadas PTRA13265: Transformadores S/E Magangué 500/110 kV | M70: No aplica | N70: No aplica | O70: 1 | P70: 0
A71: Caribe | B71: GCM | C71: 2 | D71: Valledupar 1 220/34,5/13,8 kV / Valledupar 12 220/34,5/13,8 kV | E71: "+TrfVal2372","+TrfVal2312" | F71: 52 | G71: SI | H71: Dependiente de la demanda en Valledupar 34,5 y 13.8 kV | I71: Evaluar suficiencia ESPS asociados a sobrecarga de Valledupar 220/34,5/13,8 kV | J71: PTRA05302: Nueva San Juan 110 kV | K71: PTRA05302 | M71: No aplica | N71: No aplica | O71: 1 | P71: 0
A72: Caribe | B72: GCM | C72: 3 | D72: Valledupar 12 220/34,5/13,8 kV / Valledupar 1 220/34,5/13,8 kV | E72: "+TrfVal2312","+TrfVal2372" | F72: 48 | G72: SI | H72: Dependiente de la demanda en Valledupar 34,5 y 13.8 kV | I72: Evaluar suficiencia ESPS asociados a sobrecarga de Valledupar 220/34,5/13,8 kV | J72: PTRA05302: Nueva San Juan 110 kV | K72: PTRA05302 | M72: No aplica | N72: No aplica | O72: 1 | P72: 0
A73: Caribe | B73: GCM | C73: 4 | D73: Santa Marta 1 220/110/34,5 kV /Santa Marta 2 220/110/34,5 kV + Santa Marta 9 220/110/34,5 kV | E73: "+TrfSmt2131","+TrfSmt2132","+TrfSmt2133" | F73: 155 | G73: SI | H73: Dependiente de la demanda, evaluar suficiencia del ESPS por sobrecarga en esta transformación. Tambien se puede generar sobrecarga por el devanado de 110 kV. (No cuenta con ESP) | I73: No es controlable con generación. Al evaluar N-1 si la sobrecarga es BT 34,5 kV evaluar la pertinencia de desatención de demanda. Si es del devanado 110 kV, evaluar balance de potencia reactiva en la transformación Santa Marta y Rio Córdoba 220/110 kV o evaluar la pertinencia de desatención de demanda a nivel de 110 kV | J73: PTRA06813 Burechce 110 kV, Se recomienda evaluar traslados de carga de Santa Marta 34.5 kV | K73: PTRA06813 | M73: No aplica | N73: No aplica | O73: 0 | P73: 0
A74: Caribe | B74: GCM | C74: 5 | D74: Santa Marta 2 220/110/34,5 kV /Santa Marta 1 220/110/34,5 kV + Santa Marta 9 220/110/34,5 kV | E74: "+TrfSmt2132","+TrfSmt2131","+TrfSmt2133" | F74: 155 | G74: SI | H74: Dependiente de la demanda, evaluar suficiencia del ESPS por sobrecarga en esta transformación. Tambien se puede generar sobrecarga por el devanado de 110 kV. (No cuenta con ESP) | I74: No es controlable con generación. Al evaluar N-1 si la sobrecarga es BT 34,5 kV evaluar la pertinencia de desatención de demanda. Si es del devanado 110 kV, evaluar balance de potencia reactiva en la transformación Santa Marta y Rio Córdoba 220/110 kV o evaluar la pertinencia de desatención de demanda a nivel de 110 kV | J74: PTRA06813 Burechce 110 kV, Se recomienda evaluar traslados de carga de Santa Marta 34.5 kV | K74: PTRA06813 | M74: No aplica | N74: No aplica | O74: 0 | P74: 0
A75: Caribe | B75: GCM | C75: 6 | D75: Santa Marta 9 220/110/34,5 kV /Santa Marta 1 220/110/34,5 kV + Santa Marta 2 220/110/34,5 kV | E75: "+TrfSmt2133","+TrfSmt2131","+TrfSmt2132" | F75: 155 | G75: SI | H75: Dependiente de la demanda, evaluar suficiencia del ESPS por sobrecarga en esta transformación. Tambien se puede generar sobrecarga por el devanado de 110 kV. (No cuenta con ESP) | I75: No es controlable con generación. Al evaluar N-1 si la sobrecarga es BT 34,5 kV evaluar la pertinencia de desatención de demanda. Si es del devanado 110 kV, evaluar balance de potencia reactiva en la transformación Santa Marta y Rio Córdoba 220/110 kV o evaluar la pertinencia de desatención de demanda a nivel de 110 kV | J75: PTRA06813 Burechce 110 kV, Se recomienda evaluar traslados de carga de Santa Marta 34.5 kV | K75: PTRA06813 | M75: No aplica | N75: No aplica | O75: 0 | P75: 0
A76: Caribe | B76: GCM | C76: 7 | D76: Loma – El Copey 500 kV / La Jagua – Codazzi 110 kV | E76: "-LinCopLom512","-linCodJag11" | F76: 270 | G76: NO | H76: Alta generación en la solar Latam y EL Paso con baja generación en otros recursos de la subárea GCM | I76: • Balance de generación entre los rescursos solares Latam y El Paso y la generación al interior de la subárea | J76: PTRA00325 UPME 06 - 2017 S/E Colectora 1 500 kV, LT doble circuito Colectora - Cuestecitas 500 kV y LT Cuestecitas - La Loma 500 kV | K76: PTRA00325 | L76: Evaluar aumento de capacidad del conductor. Implementar ESPS | M76: Latam y El Paso | N76: Guajira, Termonorte | O76: 3 | P76: 0
A77: Caribe | B77: GCM | C77: 8 | D77: Loma – El Copey 500 kV / El Paso – EL Copey 110 kV | E77: "-LinCopLom512","-LinCopEPa11" | F77: 320 | G77: NO | H77: Alta generación en la solar Latam y EL Paso con baja generación en otros recursos de la subárea GCM | I77: • Balance de generación entre los rescursos solares Latam y El Paso y la generación al interior de la subárea | J77: PTRA00325 UPME 06 - 2017 S/E Colectora 1 500 kV, LT doble circuito Colectora - Cuestecitas 500 kV y LT Cuestecitas - La Loma 500 kV | K77: PTRA00325 | L77: Evaluar aumento de capacidad del conductor. Implementar ESPS | M77: Latam y El Paso | N77: Guajira, Termonorte | O77: 3 | P77: 0
A78: Caribe | B78: GCM | C78: 9 | D78: Copey 5 220/110 kV / Copey 1 220/110 kV | E78: "+TrfCop25P","+TrfCop2131" | F78: 30 | G78: SI | H78: Con barras Copey 34.5 kV acopladas. Alta demanda en El Copey 34.5_kV B1 y El Copey 34.5_kV B2 | I78: Operar con las barras de Copey 34.5 kV desacopladas (abrir interruptor 5100) y desacoplar el SDL aguas abajo. | J78: No hay obra de expansión definida en el horizonte de Mediano Plazo. | O78: 0 | P78: 0
A79: Caribe | B79: GCM | C79: 10 | D79: Cuestecitas 500/230 kV / Alta Tension en Cuestecitas 500 kV | G79: SI | H79: Escenarios de media y baja demanda | I79: Mantener un perfil de tensión en Copey 500 kV menor a 515 kV | M79: No aplica | N79: No aplica | O79: 3 | P79: 0
A80: Caribe | B80: GCM | C80: 11 | D80: Alta tensión en nodos de la subárea GCM en red completa | F80: - | G80: No | H80: Escenarios de media y baja demanda | I80: Realizar gestión con recursos para el control de potencia reactiva, en caso de requerirse abrir uno o dos circuitos Nueva Cuestecitas - El Copey 1 y 2 500 kV | J80: No hay obra de expansión definida en el horizonte de Mediano Plazo. | M80: No aplica | N80: No aplica | O80: 3 | P80: 1
A81: Caribe | B81: GCM | C81: 12 | D81: Sobrecarga en red completa Santa Marta 1 220/110/34.5 kV | E81: "+TrfSmt2131" | F81: 65 | G81: NO | H81: Demanda máxima | I81: Evaluar realizar desatención de demanda. | J81: PTRA06813 Burechce 110 kV, Se recomienda evaluar traslados de carga de Santa Marta 34.5 kV | K81: PTRA06813 | M81: No aplica | N81: No aplica | O81: 1 | P81: 1
A82: Caribe | B82: GCM | C82: 13 | D82: Sobrecarga en red completa Santa Marta 2 220/110/34.5 kV | E82: "+TrfSmt2132" | F82: 65 | G82: NO | H82: Demanda máxima | I82: Evaluar realizar desatención de demanda. | J82: PTRA06813 Burechce 110 kV, Se recomienda evaluar traslados de carga de Santa Marta 34.5 kV | K82: PTRA06813 | M82: No aplica | N82: No aplica | O82: 1 | P82: 1
A83: Caribe | B83: GCM | C83: 14 | D83: Sobrecarga en red completa Santa Marta 9 220/110/34.5 kV | E83: "+TrfSmt2133" | F83: 65 | G83: NO | H83: Demanda máxima | I83: Evaluar realizar desatención de demanda. | J83: PTRA06813 Burechce 110 kV, Se recomienda evaluar traslados de carga de Santa Marta 34.5 kV | K83: PTRA06813 | M83: No aplica | N83: No aplica | O83: 1 | P83: 1
A84: Caribe | B84: GCM | C84: 15 | D84: Sobrecarga en red completa Valledupar 1 220/34.5/13.8 kV | E84: "+TrfVal2372" | F84: 45 | G84: NO | H84: Demanda máxima | I84: Evaluar realizar desatención de demanda. | J84: No hay obra de expansión definida en el horizonte de Mediano Plazo. | M84: No aplica | N84: No aplica | O84: 1 | P84: 1
A85: Caribe | B85: GCM | C85: 16 | D85: Sobrecarga en red completa Valledupar 12 220/34.5/13.8 kV | E85: "+TrfVal2312" | F85: 45 | G85: NO | H85: Demanda máxima | I85: Evaluar realizar desatención de demanda. | J85: No hay obra de expansión definida en el horizonte de Mediano Plazo. | M85: No aplica | N85: No aplica | O85: 1 | P85: 1
A86: Caribe | B86: GCM | C86: 17 | D86: Sobrecarga en red completa Valledupar 3 220/34.5/13.8 kV | E86: "+TrfVal3" | F86: 45 | G86: NO | H86: Demanda máxima | I86: Evaluar realizar desatención de demanda. | J86: No hay obra de expansión definida en el horizonte de Mediano Plazo. | M86: No aplica | N86: No aplica | O86: 1 | P86: 1
A87: Caribe | B87: GCM | C87: 18 | D87: Sobrecarga en red completa Valledupar - Guatapurí 110 kV | E87: "-LinGuaVal1" | F87: 80 | G87: NO | H87: Demanda máxima | I87: Evaluar realizar desatención de demanda. | J87: PTRA05302: Nueva San Juan 110 kV | M87: No aplica | N87: No aplica | O87: 1 | P87: 1
A88: Caribe | B88: Cerromatoso | C88: 1 | D88: Cerromatoso 1 500/110 kV / Cerromatoso 2 500/110 kV + Cerromatoso 4 500/110 kV | E88: +TrfCmt5131,"+TrfCmt5132","+TrfCmt3" | F88: 290 | G88: NO | H88: Escenarios de alta demanda con baja generacion aguas debajo de Cerromatoso 110 kV | I88: Programar generacion en Gecelca III | J88: No hay obra de expansión definida en el horizonte de mediano plazo | M88: No aplica | N88: Gecelca III | O88: 0 | P88: 0
A89: Caribe | B89: Cerromatoso | C89: 2 | D89: Cerromatoso 2 500/110 kV / Cerromatoso 1 500/110 kV + Cerromatoso 4 500/110 kV | E89: +TrfCmt5131,"+TrfCmt5132","+TrfCmt3" | F89: 290 | G89: NO | H89: Escenarios de alta demanda con baja generacion aguas debajo de Cerromatoso 110 kV | I89: Programar generacion en Gecelca III | J89: No hay obra de expansión definida en el horizonte de mediano plazo | M89: No aplica | N89: Gecelca III | O89: 0 | P89: 0
A90: Caribe | B90: Cerromatoso | C90: 3 | D90: Cerromatoso 4 500/110 kV / Cerromatoso 1 500/110 kV + Cerromatoso 2 500/110 kV | E90: +TrfCmt5131,"+TrfCmt5132","+TrfCmt3" | F90: 290 | G90: NO | H90: Escenarios de alta demanda con baja generacion aguas debajo de Cerromatoso 110 kV | I90: Programar generacion en Gecelca III | J90: No hay obra de expansión definida en el horizonte de mediano plazo | M90: No aplica | N90: Gecelca III | O90: 0 | P90: 0
A91: Caribe | B91: Cerromatoso | C91: 4 | D91: Agotamiento capacidad de cortocircuito de Cerromatoso 110 kV | G91: NO | H91: En línea un alto número de recursos de generación cercanos eléctricamente | I91: Con recursos de generación de la subárea en línea de identificar que se supera la capacidad de corto circuito de Cerromatoso 110 kV, validar la pertinencia de operar Cerromatoso con los campos repartidos en dos barras y el acoplamiento abierto para distribuir los aportes de corto circuito y mitigar esta condición | J91: No hay obra de expansión definida en el horizonte de Mediano Plazo. Se requiere evaluar la pertinencia de aumentar la capacidad de corto circuito de Cerromatoso 110 kV (capacidad actual 25 KA) | O91: 2 | P91: 1
A92: Antioquia | B92: Antioquia | C92: 1 | D92: Sierra – Primavera 230 kV / Sierra - San Carlos 230 kV | E92: "+LinPmvSie21","+LinScaSie22" | F92: 417 | G92: NO | H92: Demanda máxima, media y mínima. Baja generación en Antioquia y Caribe, alta generación en Oriental y en Termosierra. | I92: Balancear generación entre todas las áreas del SIN. La acción de mayor efectividad para controlar el corte consiste en bajar generación en La Sierra. | J92: No hay obra de expansión definida en el horizonte de mediano plazo | M92: Sierra | N92: San Carlos, Porce II, Porce III, La Tasajera | O92: 3 | P92: 0
A93: Antioquia | B93: Antioquia | C93: 2 | D93: Bolombolo - Barroso 110 kV / Baja tensión red 115 kV Dispac | F93: - | H93: Todos los escenarios de demanda sin generación de la PCH Barroso | I93: Emplear recursos de soporte de tensión en la zona, incluídas las centrales de generación Barroso 1 y 2, para aumentar el perfil de tensión en las subestaciones del departamento | J93: PTRA13267: UPME STR 01 - 2024 SVC de 30 MVAr en S/E Cértegui 115 kV. FPO:31/12/2027 (Declarada desierta) PTRA00389: S/E Nuevo Quibdó 115 kV y líneas asociadas. FPO:31/12/2030 (Sin Promotor). PTRA13502: S/E Nueva Quibdó 220 kV. FPO:31/12/2030 (Sin Promotor). | M93: No aplica | N93: PCH Barroso | O93: 0 | P93: 0
A94: Antioquia | B94: Antioquia | C94: 3 | D94: Barroso - El Siete 115 kV / Baja tensión red 115 kV Dispac | F94: - | H94: Todos los escenarios de demanda | M94: No aplica | N94: PCH Barroso | O94: 0 | P94: 0
A95: Antioquia | B95: Antioquia | C95: 4 | D95: Quibdó - El Siete 115 kV / Baja tensión red 115 kV Dispac | F95: - | H95: Todos los escenarios de demanda | M95: No aplica | N95: PCH Barroso | O95: 0 | P95: 0
A96: Antioquia | B96: Antioquia | C96: 5 | D96: Cértegui - Virginia 115 kV / Baja tensión red 115 kV Dispac | F96: - | H96: Todos los escenarios de demanda | M96: No aplica | N96: PCH Barroso | O96: 0 | P96: 0
A97: Antioquia | B97: Antioquia | C97: 6 | D97: Quibdó - Cértegui 115 kV / Baja tensión red 115 kV Dispac | F97: - | H97: Demanda máxima y media sin generación de la PCH Barroso | M97: No aplica | N97: PCH Barroso | O97: 0 | P97: 0
A98: Antioquia | B98: Antioquia | C98: 7 | D98: Ancón Sur (EPM) - Amagá 110 kV / Baja tensión red 115 kV Dispac | F98: - | G98: NO | H98: Demanda máxima con baja generación en Barroso y Bolombolo | I98: Emplear recursos de soporte de tensión en la zona, incluídas las centrales de generación Barroso 1 y 2, para aumentar el perfil de tensión en las subestaciones del departamento | J98: PTRA00476: UPME 03-2021 Subestación Carrieles 230 kV (Antes S/E Hispania 230 kV) PTRA01152: Nueva subestación Carrieles 110 kV. Transformadores de conexión 220/110 - 2 x 180 MVA PTRA13267: UPME STR 01 - 2024 SVC de 30 MVAr en S/E Cértegui 115 kV. FPO:31/12/2027 (Declarada desierta) PTRA00389: S/E Nuevo Quibdó 115 kV y líneas asociadas. FPO:31/12/2030 (Sin Promotor). PTRA13502: S/E Nueva Quibdó 220 kV. FPO:31/12/2030 (Sin Promotor). | M98: No aplica | N98: PCH Barroso | O98: 0 | P98: 0
A99: Antioquia | B99: Antioquia | C99: 8 | D99: Amagá - Bolombolo 1 110 kV / Baja tensión red 115 kV Dispac | F99: - | G99: NO | M99: No aplica | N99: PCH Barroso | O99: 0 | P99: 0
A100: Antioquia | B100: Antioquia | C100: 9 | D100: Sobrecarga de Barbosa - Girardota 1 110 kV | E100: "+CI0807" | F100: 95 | G100: NO | H100: Demanda máxima con baja generación de las plantas menores en Antioquia | I100: Aumentar la generación de Carlos lleras. | J100: No hay obra de expansión definida en el horizonte de mediano plazo | M100: No aplica | N100: Carlos Lleras | O100: 3 | P100: 1
...

Sheet Restricciones SDL
A1: Area | B1: Subárea | C1: Número | D1: Restricción | E1: FKEYS | F1: Corte [MW] | G1: ESPS | H1: Escenario | I1: Recomendación operativa | J1: Proyecto de Expansión Mediano plazo | K1: Codigo | L1: Acciones de corto plazo recomendadas | M1: Generación a limitar | N1: Generación a subir | O1: Estado restricción | P1: Origen de la restricción
A2: Caribe | B2: Atlántico | C2: 1 | D2: Las Flores 1 110/34.5 kV / Las Flores 2 110/34.5 kV | E2: "+TR0456","+TR0531" | F2: 60 | G2: NO | H2: Independiente del escenario de generación. En demanda máxima y media. | I2: • No hay manera de cubrir esta restricción ni de disminuir su impacto, por lo que se presentaría desatención de demanda de manera descontrolada. • Para cubrirla sería necesario programar DNA preventiva si aplica la CREG 224 de 2016 • Cabe resaltar que este valor de corte es dependiente del escenario de generación, por lo que puede existir un valor diferente dependiendo de la manera como se cubra. | J2: No hay obra de expansión definida en el horizonte de Mediano Plazo. Sí bien las SAEB tienen impacto positivo esta restricción no hace parte de su lógica. Se requieren definir TDC, obras a nivel de SDL, o proyectos de expansión • Evaluar la pertinencia de instalar un ESPS | L2: Evaluar el aumeto de capacidad de transporte de corriente del circuito. Se recomienda al OR evaluar la implementación de un esquema suplementario para mitigar el impacto de la restricción | M2: No aplica | N2: No aplica | O2: 1 | P2: 0
A3: Caribe | B3: Atlántico | C3: 2 | D3: Las Flores 2 110/34.5 kV / Las Flores 1 110/34.5 kV | E3: "+TR0531","+TR0456" | F3: 60 | G3: NO | H3: Independiente del escenario de generación. En demanda máxima y media. | I3: • No hay manera de cubrir esta restricción ni de disminuir su impacto, por lo que se presentaría desatención de demanda de manera descontrolada. • Para cubrirla sería necesario programar DNA preventiva si aplica la CREG 224 de 2016 • Cabe resaltar que este valor de corte es dependiente del escenario de generación, por lo que puede existir un valor diferente dependiendo de la manera como se cubra. | J3: No hay obra de expansión definida en el horizonte de Mediano Plazo. Sí bien las SAEB tienen impacto positivo esta restricción no hace parte de su lógica. Se requieren definir TDC, obras a nivel de SDL, o proyectos de expansión • Evaluar la pertinencia de instalar un ESPS | L3: Evaluar el aumeto de capacidad de transporte de corriente del circuito. Se recomienda al OR evaluar la implementación de un esquema suplementario para mitigar el impacto de la restricción | M3: No aplica | N3: No aplica | O3: 1 | P3: 0
A4: Caribe | B4: Atlántico | C4: 3 | D4: Silencio 4N 110/34.5 / Las Flores 1 110/34.5 + Las Flores 2 110/34.5 | E4: "+TrfSil1374","+TR0456","+TR0531" | F4: 120 | G4: NO | H4: Independiente del escenario de generación. En demanda máxima y media. | I4: • No hay manera de cubrir esta restricción ni de disminuir su impacto, por lo que se presentaría desatención de demanda de manera descontrolada. • Para cubrirla sería necesario programar DNA preventiva si aplica la CREG 224 de 2016 • Cabe resaltar que este valor de corte es dependiente del escenario de generación, por lo que puede existir un valor diferente dependiendo de la manera como se cubra. | J4: No hay obra de expansión definida en el horizonte de Mediano Plazo., si bien las SAEB tienen impacto positivo esta restricción no hace parte de su lógica. Se requieren definir TDC, obras a nivel de SDL, o proyectos de expansión • Evaluar la pertinencia de instalar un ESPS | L4: Evaluar el aumeto de capacidad de transporte de corriente del circuito. Se recomienda al OR evaluar la implementación de un esquema suplementario para mitigar el impacto de la restricción | M4: No aplica | N4: No aplica | O4: 1 | P4: 0
A5: Caribe | B5: Atlántico | C5: 4 | D5: Silencio 5 110/34.5 / Las Flores 1 110/34.5 + Las Flores 2 110/34.5 | E5: "+TR0466","+TR0456","+TR0531" | F5: 120 | G5: NO | H5: Independiente del escenario de generación. En demanda máxima y media. | I5: • No hay manera de cubrir esta restricción ni de disminuir su impacto, por lo que se presentaría desatención de demanda de manera descontrolada. • Para cubrirla sería necesario programar DNA preventiva si aplica la CREG 224 de 2016 • Cabe resaltar que este valor de corte es dependiente del escenario de generación, por lo que puede existir un valor diferente dependiendo de la manera como se cubra. | J5: No hay obra de expansión definida en el horizonte de Mediano Plazo. si bien las SAEB tienen impacto positivo esta restricción no hace parte de su lógica. Se requieren definir TDC, obras a nivel de SDL, o proyectos de expansión • Evaluar la pertinencia de instalar un ESPS | L5: Evaluar el aumeto de capacidad de transporte de corriente del circuito. Se recomienda al OR evaluar la implementación de un esquema suplementario para mitigar el impacto de la restricción | M5: No aplica | N5: No aplica | O5: 1 | P5: 0
A6: Caribe | B6: Bolívar | C6: 1 | D6: Ternera 5 66/13.8/6.9 kV / Ternera 3 66/13.8/6.9 kV | E6: "+TrfTer675","+TrfTer673" | F6: 38 | G6: SI | H6: Depende de la magnitud de carga en Ternera 13.8 y 6.9 kV | I6: Verificar suficiencia ESPS Ternera 66/13.8/6.9 kV | J6: No hay proyecto definido, los traslados a Campestre y Turbaco no son suficientes | M6: No aplica | N6: No aplica | O6: 0 | P6: 1
A7: Caribe | B7: Bolívar | C7: 2 | D7: Ternera 3 66/13.8/6.9 kV / Ternera 5 66/13.8/6.9 kV | E7: "+TrfTer673","+TrfTer675" | F7: 38 | G7: SI | H7: Depende de la magnitud de carga en Ternera 13.8 y 6.9 kV | I7: Verificar suficiencia ESPS Ternera 66/13.8/6.9 kV | J7: No hay proyecto definido, los traslados a Campestre y Turbaco no son suficientes | M7: No aplica | N7: No aplica | O7: 0 | P7: 1
A8: Caribe | B8: GCM | C8: 1 | D8: Sobrecarga Valledupar 9 110/34.5 kV | E8: "+Trf1889" | F8: 37 | G8: NO | H8: Demanda media y máxima | I8: Operar con alto perfil de tensión, se requieren TDC por parte del OR | J8: No hay obra de expansión definida en el horizonte de Mediano Plazo. (con el proyecto PTRA05302: Nueva San Juan 110 kV, se revizará la posibilidad de anillar por 34.5kV) | L8: Identificar obras entre los OR y la UPME para eliminar la condición radial | M8: No aplica | N8: No aplica | O8: 1 | P8: 1
A9: Caribe | B9: GCM | C9: 2 | D9: Sobrecarga Valledupar 9 110/34.5 kV (Sentido 34.5 kV a 110 kV) | E9: "-Trf1889" | F9: 37 | G9: NO | H9: Demanda mínima con alta generación de en los recursos solares conectados en la barra 3 de Valledupar 34.5 kV. | I9: Limitar la generación de los recursos solares conectados en la barra 3 de Valledupar 34.5 kV | J9: No hay obra de expansión definida en el horizonte de Mediano Plazo. | M9: Valledupar 1, Valledupar 2 | N9: No aplica | O9: 3 | P9: 0
A10: Caribe | B10: GCM | C10: 3 | D10: Valledupar – Guatapurí 34,5 kV LN 599 / Valledupar – Guatapurí 34,5 kV LN 513 | E10: "-LinGuaVal71","-LinGuaVal72" | F10: 30 | G10: SI | H10: Dependiente de la demanda en Guatapurí 34,5 | I10: Validar suficiencia del ESPS asociado a sobrecarga de los circuitos Valledupar – Guatapurí 34,5 kV | J10: PTRA05302: Nueva San Juan 110 kV | K10: PTRA05302 | M10: No aplica | N10: No aplica | O10: 0 | P10: 1

Sheet Restricciones nuevas
A1: Area | B1: Subárea | C1: Número | D1: Restricción | E1: FKEYS | F1: Corte [MW] | G1: CAUSA | H1: Escenario | I1: Recomendación operativa | J1: Proyecto de Expansión Mediano plazo | K1: Codigo | L1: Acciones de corto plazo recomendadas | M1: Generación a limitar | N1: Generación a subir | O1: Estado restricción | P1: Origen de la restricción
A2: Oriental | B2: Bogotá | C2: 38 | D2: Bacata 1 500/120 kV / Bacata 2 500/120 kV | E2: "+TrfBac5171","+TrfBac5172" | F2: 590 | G2: Refuerza restricción existente de Bacata 2 500/120 kV / Bacata 1 500/120 kV, ya que por la sensibilidad en reactiva puede activarse primero | H2: Demanda máxima, media Baja generación al interior del área Oriental | I2: Controlar mediante taps de transformadores Bacatá 500/115 kV y compensación reactiva en la red de 115 kV. Si no es suficiente, incrementar generación al interior del área. | J2: No hay obra de expansión definida en el horizonte de Mediano Plazo | M2: No aplica | N2: Guavio, Chivor, Pagua, Zipa | O2: 3 | P2: 0
A3: Oriental | B3: Bogotá | C3: 41 | D3: Nva Esperanza - San Mateo 1 230 kV / Nva Esperanza 3 500/115/11.4 kV | E3: "+LinNEsSMa21","+TrfNvE5171" | F3: 650 | G3: El crecimiento en la demanda del Meta contribuyó a la identificación de esta contingencia, está muy cercana en sobrecarga a la que impone el límite de Oriental. Se marca debido a la sensibilidad que tiene con los escenarios de demanda. | H3: Demanda máxima en el Meta Baja generación en Oriental | I3: Incrementar generación al interior de Oriental, siendo las más efectivas Guavio y Chivor | J3: No hay obra de expansión definida en el horizonte de Mediano Plazo | M3: No aplica | N3: Guavio, Chivor | O3: 3 | P3: 0
A4: Antioquia | B4: Antioquia | C4: 18 | D4: San Carlos 2 230/500 kV / San Carlos 3 230/500 kV | E4: "-TrfSc55232","-TrfSc55233" | F4: 650 | G4: Crecimiento de recursos de generación en antioquia en niveles de 220 kV o inferiores | H4: Demanda máxima y media. Baja generación en Recursos de generación de Antioquia 500 kV y Caribe, alta generación de recursos de Antioquia 220 kV o inferiores. | I4: En orden de impacto: 1. Bajar generación en San Carlos 2. Bajar generación en Termosierra 3. Bajar generación en Porce II 4. Subir generación en Porce III 5. Subir generación Caribe | J4: No hay obra de expansión definida en el horizonte de Mediano Plazo | M4: San Carlos, Termosierra | N4: Ituango, Porce III, Urrá | O4: 3 | P4: 0
A5: Antioquia | B5: Antioquia | C5: 19 | D5: San Carlos 3 230/500 kV / San Carlos 4 230/500 kV | E5: "-TrfSc55233","-TrfSc55234" | F5: 650 | G5: Crecimiento de recursos de generación en antioquia en niveles de 220 kV o inferiores | H5: Demanda máxima y media. Baja generación en Recursos de generación de Antioquia 500 kV y Caribe, alta generación de recursos de Antioquia 220 kV o inferiores. | I5: En orden de impacto: 1. Bajar generación en San Carlos 2. Bajar generación en Termosierra 3. Bajar generación en Porce II 4. Subir generación en Porce III 5. Subir generación Caribe | J5: No hay obra de expansión definida en el horizonte de Mediano Plazo | M5: San Carlos, Termosierra | N5: Ituango, Porce III, Urrá | O5: 3 | P5: 0
A6: Antioquia | B6: Antioquia | C6: 20 | D6: San Carlos 4 230/500 kV / San Carlos 2 230/500 kV | E6: "-TrfSc55234","-TrfSc55232" | F6: 650 | G6: Crecimiento de recursos de generación en antioquia en niveles de 220 kV o inferiores | H6: Demanda máxima y media. Baja generación en Recursos de generación de Antioquia 500 kV y Caribe, alta generación de recursos de Antioquia 220 kV o inferiores. | I6: En orden de impacto: 1. Bajar generación en San Carlos 2. Bajar generación en Termosierra 3. Bajar generación en Porce II 4. Subir generación en Porce III 5. Subir generación Caribe | J6: No hay obra de expansión definida en el horizonte de Mediano Plazo | M6: San Carlos, Termosierra | N6: Ituango, Porce III, Urrá | O6: 3 | P6: 0
A7: Antioquia | B7: Antioquia | C7: 24 | D7: Agotamiento capacidad de cortocircuito de Primavera220 kV | G7: El nivel de cortocircuito se encontraba cercano al 100%. Con la entrada del proyecto PTRA03852 – Segundo Transformador Primavera 500/230 kV – 450 MVA (UPME 01 – 2023), se ve superada su capacidad nominal. | H7: En línea un alto número de recursos de generación cercanos eléctricamente | I7: Evaluar la pertinencia de disminuir el número de unidades en línea. En caso de requerirse, techar generación en:Termocentro, Termosierra. Merilectrica, San Carlos | J7: No hay obra de expansión definida en el horizonte de Mediano Plazo | M7: Termocentro, Termosierra. Merilectrica, San Carlos | O7: 2 | P7: 1
A8: Antioquia | B8: Antioquia | C8: 24 | D8: Agotamiento capacidad de cortocircuito de Central 110 kV | G8: El nivel de cortocircuito se encontraba cercano al 100%. Con la entrada del proyecto PTRA04454 – SE Industriales 110 kV, se ve superada su capacidad nominal. | H8: En línea un alto número de recursos de generación cercanos eléctricamente | I8: Evaluar la pertinencia de disminuir el número de unidades en línea. | J8: No hay obra de expansión definida en el horizonte de Mediano Plazo | O8: 2 | P8: 1
A9: Oriental | B9: Bogotá | C9: 42 | D9: Agotamiento capacidad de cortocircuito de Nva Esperanza 115 kV | H9: En línea un alto número de recursos de generación cercanos eléctricamente | I9: Evaluar la pertinencia de disminuir el número y unidades en línea | J9: No hay obra de expansión definida en el horizonte de Mediano Plazo | O9: 2 | P9: 1
A10: Suroccidental | B10: Suroccidente | C10: 1 | D10: La Virginia - San Marcos 1 500 kV / Virginia 500/230 kV | E10: "+LrtSmaVir51r","+TrfVr55231" | F10: 650 | G10: Se activa restricción debido al incremento en el límite de importación por la entrada de la S/E Alferez 500 kV | H10: Demandas máxima y media. Estas restricciones se activan cuando la importación del área es mayor a 650 MW, es decir, en un escenario con baja generación al interior del área suroccidental | I10: -Subir la generación al interior del área Suroccidental y Oriental -Bajar la generación en áreas como Antioquia y Caribe Solo en caso de ser necesario, considerar abrir el enlace Heliconia - La Virginia 500 kV | J10: No hay obra de expansión definida en el horizonte de mediano plazo | M10: No aplica | N10: Quimbo, Betania, Alto y bajo Anchicayá, Termoemcali, Termovalle, en general la generación de suroccidental | O10: 3 | P10: 0
A11: Suroccidental | B11: Suroccidente | C11: 2 | D11: Alferez - San Marcos 1 500 kV / San Marcos 230/500 kV | E11: "+LinAlfSma51","-TrfSm55231" | F11: 530 | G11: Se activa restricción debido al incremento en el límite de importación por la entrada de la S/E Alferez 500 kV | H11: Demanda minima. Alta generación en suroccidental y alta importación desde Ecuador (altos excedentes desde el suroccidente) | I11: -Bajar la generación al interior del área Suroccidental -Subir la generación en las otras áreas del SIN, especialmente Antioquia y Oriental | J11: No hay obra de expansión definida en el horizonte de mediano plazo | M11: Quimbo, Betania, Alto y bajo Anchicayá, Termoemcali, Termovalle, en general la generación de suroccidental | N11: No aplica | O11: 3 | P11: 0
A12: Suroccidental | B12: Suroccidente | C12: 3 | D12: San Marcos - La Virginia 1 500 kV / Virginia 230/500 kV | E12: "-LrtSmaVir51r","-TrfVr55231" | F12: 680
A13: Suroccidental | B13: Caquetá | C13: 2 | D13: Interruptor S200 Betania 220 kV (Barra 1-Sección 2 a Barra 1-Sección 1) / Altamira - Hobo 115 kV | E13: "-Brk06466","+CI0006" | F13: 270 | G13: Es ante un escenario particular de generación, donde se existe un desbalance en la generación de Betania. Es decir, alta generación en Betania 3 y baja generación en Betania 1 y 2. | H13: Todos los escenarios de demanda. Alta generación en Betania 3 y Baja generación en Betania 1 y 2. Alta importación desde Ecuador. Alta generación en Quimbo, Termovalle y TermoEmcali. Coordinar la entrada de operasción en Betania. | I13: Reducir importaciones desde Ecuador - Reducir generación en Quimbo - Aumentar generación en Betania 1 y 2 - Disminuir generación en Betania 3 | J13: Los siguientes proyectos permiten mitigar mas no eliminar la restricción (la nueva generación prevista vuelve a activarla) - PROG08336: Campoalaegre Solar - PTRA09586 y PTRA03843 (Huila 230/115 kV) | M13: Betania 3, Quimbo, Termoemcali y Termovalle | N13: Betania 1 y 2 | O13: 3 | P13: 0
A14: Suroccidental | B14: Huila-Tolima | C14: 1 | D14: Betania - TSeboruco 1 115 k V / Betania - Sur 1 115 kV | E14: "+LinBetSbr11","+LinBetSur11" | F14: 135 | G14: Con la repotenciación de la línea Betania - Tseboruco, ahora la restricción de nivel 1 es la que impacta a la línea sin repotencia Betania - Sur 115 kV | H14: Demandas máxima, media y mínima, en escenarios de alta generación en Betania, Quimbo, alta importación desde Ecuador, baja generación en el área oriental y alta generación en el Valle, baja generación a nivel de 115 kV en Huila-Tolima, Prado, Amoyá y Cucuana. | I14: La acción más efectiva para mitigar este corte es aumentar la generación en Prado, de igual manera se recomienda realizar los siguientes balances de generación: - Bajar la generación en Betania y Quimbo, bajar la importación desde Ecuador y bajar la generación en el Valle - Subir la generación menor de la subárea Huila -Tolima y subir la generación en Oriental | J14: No hay obra de expansión definida en el horizonte de mediano plazo | M14: Quimbo, Betania | N14: Amoya, Cucuana y Prado | O14: 3 | P14: 0
A15: Suroccidental | B15: Huila-Tolima | C15: 2 | D15: Betania - El Bote 1 115 k V / Betania - Sur 1 115 kV | E15: "+CI0063","+LinBetSur11" | F15: 135 | G15: Con la repotenciación de la línea Betania - Tseboruco, ahora la restricción de nivel 1 es la que impacta a la línea sin repotencia Betania - Sur 115 kV | M15: Quimbo, Betania | N15: Amoya, Cucuana y Prado | O15: 3 | P15: 0

Sheet Restricciones_Futuras
A1: Area | B1: Subarea | C1: Número | D1: Restricción | E1: FKEYS | F1: Corte [MW] | G1: ESPS | H1: Escenario | I1: Recomendación operativa | J1: Proyecto de Expansión Mediano plazo | K1: Codigo | L1: Acciones de corto plazo recomendadas | M1: Generación a limitar | N1: Generación a subir | O1: Estado restricción | P1: Origen de la restricción | Q1: Cuando ingresa la restricción?
A2: Suroccidental | B2: Valle | C2: Nueva | D2: Estambul – Juanchito 1 115 kV / Estambul - Juanchito 2 115 kV | E2: "+LinEstJua11", "+LinEstJua12" | F2: 170 | G2: No
A3: Antioquia | B3: Antioquia | C3: Nueva | D3: Urabá – Nueva Colonia 110 kV / Urabá – Apartadó 110 kV | E3: "+CI0806", "+LinNCoUrb11" | F3: 70 | G3: No | H3: Alta generación en las subestaciones Apartadó 110 kV y Nueva Colonia 110 kV (con el circuito Apartadó - Caucheras 110 kV abierto en un extremo). | I3: Desatender demanda en Apartadó 110 kV o Nueva Colonia 110 kV.
A4: Caribe | B4: Atlántico | C4: nueva | D4: Tebsa – Caracolí 220 kV / Tebsa – El Río 220 kV | F4: 390 | G4: NO | H4: Alta generación Tebsa y Barranquilla y baja en Flores 1 y Flores 4 | I4: • Balance de generación entre Flores 1 - Flores 4 y Tebsa - Barranquilla. | J4: No hay obra de expansión definida en el horizonte de Mediano Plazo. | M4: Tebsa, Barranquilla | N4: Flores 1, Flores 4 | O4: 0 | P4: 0 | Q4: Ingresa con los trafos de El Río 220/110kV
A5: Caribe | B5: Atlántico | C5: nueva | D5: Sabanalarga 2 500/220 kV / Sabanalarga 1 y 3 500/220 kV | F5: 880 | H5: Alta generación recursos de generación a conectar en Sabanalarga 500 kV | M5: Recursos en Sabanalarga 500 kV | N5: Genergación al interior de Caribe 2 | O5: 0 | P5: 0 | Q5: Ingresa con el proyecto Guayepo 400MW
B6: TOMA DE CARGA METRO | D6: Salitre - Chicalá 1 115 T1 kV / Colegio - Porvenir 1 115 kV | E6: "+CI0982","+LinColPor11" | F6: 150 | G6: NO | H6: Gestión de demanda. Radialidad.
B7: Occidente. | D7: Noroeste 1 230 kV/115 kV / Balsillas – Mosquera 115 kV | E7: "+TrfNor2171", "+CI0033" | F7: 230 | G7: NO | H7: Baja generación en Oriental Demanda máxima y media Subir generación en Zipa.

Sheet Restricciones_Eliminadas
A1: Area | B1: Subarea | C1: Número | D1: Restricción | E1: FKEYS | F1: Corte [MW] | G1: ESPS | H1: Escenario | I1: Recomendación operativa | J1: Proyecto de Expansión Mediano plazo | K1: Codigo | L1: Acciones de corto plazo recomendadas | M1: Generación a limitar | N1: Generación a subir | O1: Estado restricción | P1: Origen de la restricción | Q1: AAAAMMDD_NOTA
A2: Caribe | B2: Atlántico | C2: 24 | D2: Oasis - Silencio 110 kV / Oasis - Centro 110 kV | E2: "+CI0316","-CI0123" | F2: 95 | G2: SI | H2: Alta generación en Flores 1 y Flores 4 con baja generación en Tebsa y Barranquilla | I2: Balance de generación entre Flores 1 - Flores 4 y Tebsa – Barranquilla. De no ser posible eliminar esta restricción con balance de generación, verificar suficiencia ESPS sobrecarga de Oasis – Centro 110 kV | J2: PTRA00669: Convocatoria Atlántico ETAPA 4 Subestación Estadio 110 kV y circuitos asociados | K2: PTRA00669 | M2: Flores 1, Flores 4 | N2: Tebsa, Barranquilla | O2: 0 | P2: 0 | Q2: 20231102_Con el ingreso de la etapa 4 del proyectos UPME STR-02 Atlántico se eliminó esta restricción
A3: Caribe | B3: Atlántico | C3: 24 | D3: Tebsa - Unión 110 kV / Tebsa - El Río 110 kV | E3: "+CI0484","-CI0454" | F3: 140 | G3: SI | H3: Alta generación en Tebsa y Barranquilla. Baja generación en Flores 1 y Flores 4. | I3: • Balance de generación entre Flores 1 - Flores 4 y Tebsa - Barranquilla. • De no ser posible eliminar esta restricción con balance de generación, verificar suficiencia ESPS de sobrecarga de la línea Tebsa – El Río 110 kV . | J3: PTRA00669: Convocatoria Atlántico ETAPA 5 circuito Tebsa - Magdalena 110 kV | K3: PTRA00669 | M3: Tebsa, Barranquilla | N3: Flores 1, Flores 4 | O3: 1 | P3: 0 | Q3: 20231103_Con el ingreso de la etapa 5 del proyectos UPME STR-02 Atlántico se eliminó esta restricción
A4: Caribe | B4: Atlántico | C4: 25 | D4: El Río 110/34.5 kV / Tebsa - Unión 110 kV | E4: "+TR0454","+CI0484" | F4: 105 | G4: SI | H4: Independiente del escenario. | I4: • No hay manera de cubrir esta restricción ni de disminuir su impacto, por lo que se presentaría desatención de demanda de manera descontrolada. • Para cubrirla sería necesario programar DNA preventiva si aplica la CREG 224 de 2016 | J4: PTRA00669: Convocatoria Atlántico ETAPA 5 circuito Tebsa - Magdalena 110 kV | K4: PTRA00669 | L4: Evaluar el aumeto de capacidad de transporte de corriente del circuito. Se recomienda al OR evaluar la implementación de un esquema suplementario para mitigar el impacto de la restricción | M4: No aplica | N4: No aplica | O4: 1 | P4: 0
A5: Caribe | B5: Atlántico | C5: 26 | D5: Sobrecarga en del circuito Tebsa - Unión 110 kV | E5: "+CI0484" | F5: 110 | G5: SI | H5: Independiente del escenario. | I5: Si bien puede mitigarse con balance de generación, se identifica que su criticidad esta asociada principalmente a la demanda. | J5: PTRA00669: Convocatoria Atlántico ETAPA 5 circuito Tebsa - Magdalena 110 kV | K5: PTRA00669 | M5: Tebsa, Barranquilla | N5: Flores 1, Flores 4 | O5: 1 | P5: 1
A6: Caribe | B6: Atlántico | C6: 27 | D6: Tebsa - El Río 110 kV / Tebsa - Unión 110 kV | E6: "-CI0454","+CI0484" | F6: 135 | G6: SI | H6: Alta generación en Tebsa y Barranquilla. Baja generación en Flores 1 y Flores 4. | I6: • Balance de generación entre Flores 1 - Flores 4 y Tebsa – Barranquilla. • De no ser posible eliminar esta restricción con balance de generación. • Verificar suficiencia ESPS de sobrecarga de Tebsa – Cordialidad 110 kV | J6: PTRA00669: Convocatoria Atlántico ETAPA 5 circuito Tebsa - Magdalena 110 kV | K6: PTRA00669 | M6: Tebsa, Barranquilla | N6: Flores 1, Flores 4 | O6: 1 | P6: 0
A7: Caribe | B7: Cordoba-Sucre | C7: =C6+1 -> 28 | D7: Sobrecarga del transformador El Carmen 110/66/13.8 kV | E7: "+TR0522" | F7: 44 | G7: NO | H7: Demanda media y máxima | I7: En lo posible operar en sus devanados de 110 y 66 kV con una tensión alta pero segura y regulatoria. Durante el transitorio asociado a fallas, entre mayor es la carga de este equipo en menor la recuperación transitoria de tensión en nodos radiales a 66 kV que se alimentan de este equipo. | J7: PTRA01139: Carreto 500 kV y circuitos asociados. PTRA02158: Carreto 66 kV y circuitos asociados. | K7: PTRA01139, PTRA02158 | L7: Identificar obras entre los OR y la UPME para eliminar la condición radial | M7: No aplica | N7: No aplica | O7: 1 | P7: 1 | Q7: 20231029_Con la entrada en operación del segundo transformador El Carmen 110/66/13.8kV empachado con el transformador El Carmen 1 110/66/13.8kV en los niveles de tensión 110kV y 66kV
A8: Caribe | B8: GCM | C8: 2 | D8: Baja tensión en los nodos El Paso y La Jagua 110 kV en estado normal de operación y ante N-1 de La Loma – EL Copey - 500 kV o Chinú - El Copey 500 kV | G8: SI | H8: Independiente del escenario. | I8: Operar con perfil alto de tensión en nodos de la subárea GCM, buscar alta tensión en los nodos de EL Paso y La Jagua110 kV. Cubrir con MW internos las posibles restricciones por sobrecarga ante contingencia sencilla. Realizar conexión de bancos capacitivos al interior | J8: PTRA00203: Circuitos a 110 kV La Loma – La Jagua y La Loma – El Paso | K8: PTRA00203 | M8: No aplica | N8: No aplica | O8: 1 | P8: 0 | Q8: 20231201_Con el ingreso del proyecto La Loma – El Paso y La Loma - La Jagua a 110 kV se eliminan estas restricciones
A9: Caribe | B9: GCM | C9: 3 | D9: Valledupar 11 220/110 kV / Valledupar 2 220/110 kV | E9: "+TrfVll2111","+TrfVal2131" | F9: 95 | G9: SI | H9: Dependiente de la demanda | I9: Validar sufiiencia del ESPS asociado a sobrecarga del ATR Valledupar 2 220/110 kV. Evaluar la necesidad de solicitar desatención de demanda. En Valledupar 34,5 kV no cerrar interruptor 5100 sin la aprobación del equipo de protecciones | J9: PTRA00203: Circuito La Loma – La Jagua 110 kV | K9: PTRA00203 | M9: No aplica | N9: No aplica | O9: 1 | P9: 0
A10: Caribe | B10: GCM | C10: 4 | D10: Copey 1 500/220 kV / Copey 2 500/220 kV | E10: "+TrfCop5231","+TrfCop5232" | F10: 495 | G10: NO | H10: Alta importación de potencia de la subárea GCM | I10: Disminuir la importación de potencia de la subárea GCM aumentando la magnitud de generación al interior. | J10: PTRA00203: Circuitos a 110 kV La Loma – La Jagua y La Loma – El Paso PTRA00243: UPME 09 - 2016 Subestación Cuestecitas 500 kV y Líneas Copey - Cuestecitas 500 kV y Copey - Fundación 220 kV | K10: PTRA00203, PTRA00243 | M10: No aplica | N10: Guajira, Termonorte | O10: 0 | P10: 0
A11: Caribe | B11: Bolívar | C11: =Restricciones!C38+1 -> 3 | D11: Cartagena - Bocagrande 66 kV / Bosque - Bocagrande 66 kV | E11: "-CI0714","-CI0713" | F11: 40 | G11: SI | H11: Depende de la magnitud de carga en Bocagrande 66 kV | I11: • Validar suficiencia del ESPS de sobrecarga en la línea Bosque – Bocagrande 66 kV | J11: PTRA07064: Aumento de capacidad circuito Bosque – Bocagrande 66 kV (FPO: 2023) | K11: PTRA00617, PTRA07064 | M11: No aplica | N11: No aplica | O11: 1 | P11: 0 | Q11: 20231215_Actualización de parámetros técnicos de línea Bocagrande-Bosque 1 66kV
A12: Suroccidental | B12: Huila-Tolima | C12: 1 | D12: Primavera - Bacata 500 kV / Brisas - Nva Cajamarca 1 115 kV | E12: "-PmvBac500,"+LinBriNca11" | F12: 480 | G12: NO | H12: Demanda mínima. Alta generación en Huila-Tolima, Amoyá, Prado, Cucuana, Betania y Quimbo, alta generación en Oriental, generación mínima en Valle y CQR y alta importación desde Ecuador. | I12: La acción más efectiva para controlar el corte es reducir la generación en Huila – Tolima y aumentar la generación en el Valle y CQR | J12: PTRA01398: Repotenciación líneas STR-Tolima. Especialmente la repotenciación de los circuitos: CAJAMARCA - REGIVIT 115 kV y BRISAS - CAJAMARCA 115 kV de 400 A a 757 A. Fecha de entrada: 18/12/2023 | K12: PTRA01398 | M12: Betania, Quimbo, Amoyá, Prado y Cucuana | N12: Calima, Emcali, Termovalle y Salvajina | O12: 0 | P12: 0
A13: Suroccidental | B13: Huila-Tolima | C13: 2 | D13: Primavera - Bacata 500 kV / Nva Cajamarca - Regevit 1 115 kV | E13: "-PmvBac500","+LinCajNca11" | F13: 990 | G13: NO | H13: Demandas máxima y media. Alta generación en el Valle, Antioquia y Caribe, alta exportación hacia Ecuador y baja generación en Betania, Quimbo, CQR y Oriental | I13: La acción más efectiva para controlar el corte es aumentar la generación en Huila – Tolima y reducir la generación en el Valle y CQR | J13: PTRA01398: Repotenciación líneas STR-Tolima. Especialmente la repotenciación de los circuitos: CAJAMARCA - REGIVIT 115 kV y BRISAS - CAJAMARCA 115 kV de 400 A a 757 A. Fecha de entrada: 18/12/2024 | K13: PTRA01398 | M13: Quimbo, Betania y Oriental. | N13: Antioquia y Valle | O13: 0 | P13: 0
A14: Suroccidental | B14: Valle | C14: 3 | D14: Agotamiento capacidad de cortocircuito de Juanchito 115 kV | G14: NO | H14: En línea un alto número de recursos de generación cercanos eléctricamente | J14: Aumento de capacidad de corto circuito a de 26.2 kA a 40 kA | O14: 2 | P14: 1 | Q14: 20231226_Actualización de parámetros por parte del OR
A15: Caribe | B15: Atlántico | C15: 11 | D15: Caracolí – Malambo 1 110 kV / Caracolí – Malambo 2 110 kV | E15: "+LinCrcMal11","+LinCrcMal12" | F15: 120 | G15: NO | H15: Dependiente del escenario de generación | I15: • Balance de generación entre Solar Caracolí - Flores 1 - Flores 4 y Tebsa - Barranquilla. | J15: No hay obra de expansión definida en el horizonte de Mediano Plazo. | M15: Solar Caracolí | N15: No aplica | O15: 0 | P15: 0 | Q15: 20240319_La demanda del MP y los proyectos de generación aún no activa esta restricción
A16: Caribe | B16: Atlántico | C16: =C15+1 -> 12 | D16: Unión 110/34.5 kV / El Río - Magdalena 34.5 kV | E16: "+TR0483","+CI0743-2" | F16: 55 | G16: NO | H16: Independiente del escenario. | I16: • No hay manera de cubrir esta restricción ni de disminuir su impacto, por lo que se presentaría desatención de demanda de manera descontrolada. • Para cubrirla sería necesario programar DNA preventiva si aplica la CREG 224 de 2016 | J16: Traslados de carga que realizará AIR-E a la subestación Magdalena 110 kV (FPO: 2025) • Evaluar la pertinencia de instalar un ESPS | L16: Evaluar el aumeto de capacidad de transporte de corriente del circuito. Se recomienda al OR evaluar la implementación de un esquema suplementario para mitigar el impacto de la restricción | M16: No aplica | N16: No aplica | O16: 1 | P16: 0 | Q16: 20240319_Esta restricción se elimina por el ingreso de Magdalena 110kV
A17: Antioquia | B17: Antioquia | C17: 7 | D17: Calizas – Rio Claro 1 110 kV / Calderas – Guatapé 1 110 kV | E17: "+LinClzRcl11","+NOR-CLD-GTP1" | F17: 110 | G17: NO | H17: Demanda mínima con alta generación de las plantas menores en Antioquia | I17: Bajar generación en las unidades de San Miguel y menores (<20MW). | J17: PTRA00324: UPME 10 -2021 Subestación San Lorenzo 230 kV. | M17: Calderas, Popal, San Miguel, San Matías, El Molino | N17: No aplica | O17: 0 | P17: 0 | Q17: 20240321_En el horizonte analizado no se observó la restricción
A18: Oriental | B18: Meta | C18: 2 | D18: Reforma 3 230/115 kV / Reforma 2 230/115 kV | E18: "+TrfRef2173","+Trfref2172" | F18: 310 | G18: NO | H18: En escenarios de baja generación interna en el Meta y demanda alta, esta sobrecarga podría no ser controlada mediante balances de generación, por lo cual se recomienda que ante dicho escenario se considere desatención de demanda o el traslado de carga a la subestación Villavicencio 115 kV. | I18: En escenarios de baja generación interna en el Meta y demanda alta, esta sobrecarga podría no ser controlada mediante balances de generación, por lo cual se recomienda que ante dicho escenario se considere desatención de demanda o el traslado de carga a la subestación Villavicencio 115 kV. | J18: PTRA00623: Etapa 2 Transformadores Santa Helena 230/115 kV 2X150 MVA (Suria 2) | K18: PTRA00623 | L18: Evaluar el aumeto de capacidad de transporte de corriente del circuito. Se recomienda al OR evaluar la implementación de un esquema suplementario para mitigar el impacto de la restricción | M18: No aplica | N18: No aplica | O18: 3 | P18: 0 | Q18: 20240912_Esta restricción se elimina, ya que existe una más restrictiva Reforma 3 230/115 kV / Reforma 1 230/115 kV
A19: Oriental | B19: Meta | C19: 4 | D19: Reforma - Barzal 115 kV / Reforma - Ocoa 1 115 kV | E19: "-LinBrzVil11","-CI1043" | F19: 300 | G19: NO | H19: En escenarios de baja generación interna en el Meta y demanda alta, esta sobrecarga podría no ser controlada mediante balances de generación, por lo cual se recomienda que ante dicho escenario se considere desatención de demanda o el traslado de carga a la subestación Villavicencio 115 kV. | I19: En escenarios de baja generación interna en el Meta y demanda alta, esta sobrecarga podría no ser controlada mediante balances de generación, por lo cual se recomienda que ante dicho escenario se considere desatención de demanda o el traslado de carga a la subestación Villavicencio 115 kV. | J19: PTRA00623: Etapa 2 Transformadores Santa Helena 230/115 kV 2X150 MVA (Suria 2) | K19: PTRA00623 | L19: Evaluar el aumeto de capacidad de transporte de corriente del circuito. Se recomienda al OR evaluar la implementación de un esquema suplementario para mitigar el impacto de la restricción | M19: No aplica | N19: No aplica | O19: 3 | P19: 0 | Q19: 20240912_Esta restricción se elimina, ya que existe una más restrictiva Reforma 3 230/115 kV / Reforma 1 230/115 kV
A20: Oriental | B20: Meta | C20: 5 | D20: Reforma - Barzal 115 kV / Reforma - Ocoa 2 115 kV | E20: "-LinBrzVil11","-CI1042" | F20: 300 | G20: NO | H20: En escenarios de baja generación interna en el Meta y demanda alta, esta sobrecarga podría no ser controlada mediante balances de generación, por lo cual se recomienda que ante dicho escenario se considere desatención de demanda o el traslado de carga a la subestación Villavicencio 115 kV. | I20: En escenarios de baja generación interna en el Meta y demanda alta, esta sobrecarga podría no ser controlada mediante balances de generación, por lo cual se recomienda que ante dicho escenario se considere desatención de demanda o el traslado de carga a la subestación Villavicencio 115 kV. | J20: PTRA00623: Etapa 2 Transformadores Santa Helena 230/115 kV 2X150 MVA (Suria 2) | K20: PTRA00623 | L20: Evaluar el aumeto de capacidad de transporte de corriente del circuito. Se recomienda al OR evaluar la implementación de un esquema suplementario para mitigar el impacto de la restricción | M20: No aplica | N20: No aplica | O20: 3 | P20: 0 | Q20: 20240912_Esta restricción se elimina, ya que existe una más restrictiva Reforma 3 230/115 kV / Reforma 1 230/115 kV
A21: Oriental | B21: Meta | C21: 6 | D21: Reforma - Ocoa 2 115 kV / Reforma - Ocoa 1 115 kV | E21: "-CI1043","-CI1042" | F21: 200 | G21: NO | H21: En escenarios de baja generación interna en el Meta y demanda alta, esta sobrecarga podría no ser controlada mediante balances de generación, por lo cual se recomienda que ante dicho escenario se considere desatención de demanda o el traslado de carga a la subestación Villavicencio 115 kV. | I21: En escenarios de baja generación interna en el Meta y demanda alta, esta sobrecarga podría no ser controlada mediante balances de generación, por lo cual se recomienda que ante dicho escenario se considere desatención de demanda o el traslado de carga a la subestación Villavicencio 115 kV. | J21: PTRA00623: Etapa 2 Transformadores Santa Helena 230/115 kV 2X150 MVA (Suria 2) | K21: PTRA00623 | L21: Evaluar el aumeto de capacidad de transporte de corriente del circuito. Se recomienda al OR evaluar la implementación de un esquema suplementario para mitigar el impacto de la restricción | M21: No aplica | N21: No aplica | O21: 3 | P21: 0 | Q21: 20240912_Esta restricción se elimina, ya que existe una más restrictiva Reforma 3 230/115 kV / Reforma 1 230/115 kV
A22: Oriental | B22: Meta | C22: 7 | D22: Reforma - Ocoa 1 115 kV / Reforma - Ocoa 2 115 kV | E22: "-CI1042","-CI1043" | F22: 200 | G22: NO | H22: En escenarios de baja generación interna en el Meta y demanda alta, esta sobrecarga podría no ser controlada mediante balances de generación, por lo cual se recomienda que ante dicho escenario se considere desatención de demanda o el traslado de carga a la subestación Villavicencio 115 kV. | I22: En escenarios de baja generación interna en el Meta y demanda alta, esta sobrecarga podría no ser controlada mediante balances de generación, por lo cual se recomienda que ante dicho escenario se considere desatención de demanda o el traslado de carga a la subestación Villavicencio 115 kV. | J22: PTRA00623: Etapa 2 Transformadores Santa Helena 230/115 kV 2X150 MVA (Suria 2) | K22: PTRA00623 | L22: Evaluar el aumeto de capacidad de transporte de corriente del circuito. Se recomienda al OR evaluar la implementación de un esquema suplementario para mitigar el impacto de la restricción | M22: No aplica | N22: No aplica | O22: 3 | P22: 0 | Q22: 20240912_Esta restricción se elimina, ya que existe una más restrictiva Reforma 3 230/115 kV / Reforma 1 230/115 kV
A23: Oriental | B23: Bogotá | C23: 11 | D23: Bacata - Chia 1 115 kV / Bacata - El Sol 1 115 kV | E23: "+LinBacCh11","+LinBacSol11" | F23: 210 | G23: NO | H23: Guateque Sesquilé 115 kV Abierto. Baja generación en Zipa. | I23: Con Guateque Sesquilé 115 kV Abierto: Incremento de generación en Zipa. | J23: No hay obra de expansión definida en el horizonte de Mediano Plazo | N23: Zipa | O23: 3 | P23: 0 | Q23: 20240912_Esta restricción se elimina, ya que se mitiga con la repotenciación de las líneas en Sabana Norte. Se agrega una nueva restricción que corresponde a Bacata - El Sol 1 115 kV / Chia - Diaco 1 115 kV

Sheet ReqUnidades_Caribe2
A1: Demanda_MW_inf | B1: Demanda_MW_sup | C1: Caribe2 | D1: 1201-1300 | E1: 1301-1400
A2: 0 | B2: 1539.9999 | C2: 2 | D2: 0 | E2: 0
A3: =B2+0.0001 -> 1540 | B3: 1612.9999 | C3: 1.6 | D3: 0 | E3: 0.4
A4: =B3+0.0001 -> 1613 | B4: 1755.9999 | D4: 0 | E4: 1.5
A5: =B4+0.0001 -> 1756 | B5: 1896.9999 | D5: 0 | E5: 2.5
A6: =B5+0.0001 -> 1897 | B6: 2036.9999 | D6: 0 | E6: 3.3
A7: =B6+0.0001 -> 2037 | B7: 2176.9999 | D7: 0 | E7: 5
A8: =B7+0.0001 -> 2177 | B8: 2257.9999 | C8: 6 | D8: 0 | E8: 0.5
A9: =B8+0.0001 -> 2258 | B9: 2339.9999 | C9: 6.5 | D9: 0 | E9: 0.5
A10: =B9+0.0001 -> 2340 | B10: 2421.9999 | C10: 7.5 | D10: 0 | E10: 1
A11: =B10+0.0001 -> 2422 | B11: 2510.9999 | C11: 8 | D11: 0 | E11: 1
A12: =B11+0.0001 -> 2511 | B12: 2599.9999 | C12: 9 | D12: 0 | E12: 1
A13: =B12+0.0001 -> 2600 | B13: 2800 | C13: 10 | D13: 0 | E13: 1
A14: =B13+0.0001 -> 2800.0001 | B14: 2900 | C14: 10.5 | D14: 0 | E14: 1
A15: =B14+0.0001 -> 2900.0001 | B15: 3000 | C15: 11.2 | D15: 0 | E15: 1

Sheet ReqUnidades_Suroccidental
A1: Demanda_MW_inf | B1: Demanda_MW_sup | C1: Suroccidental | D1: Cubrir con unidades de Betania, Quimbo, Salvajina y Alto Anchicayá | E1: Betania, Quimbo Unidades físicas | F1: Salvajina, Alto Anchicaya Unidades físicas
A2: 1150 | B2: 1250 | C2: 1.79 | D2: 1.79 | E2: 1 | F2: 1
A3: 1250 | B3: 1350 | C3: 1.64 | D3: 1.64 | E3: 1 | F3: 1
A4: 1350 | B4: 1450 | C4: 1.22 | D4: 1.22 | E4: 1 | F4: 1
A5: 1450 | B5: 1550
A6: 1550 | B6: 1650
A7: 1650 | B7: 1750
A8: 1750 | B8: 1850 | C8: 0.4
A9: 1850 | B9: 1950 | C9: 0.55
A10: 1950 | B10: 2050 | C10: 0.68
A11: 2050 | B11: 2150 | C11: 1.87 | D11: 0.56
A12: 2150 | B12: 2250 | C12: 2.54 | D12: 0.56
A13: 2250 | B13: 2350 | C13: 3.15 | D13: 1.15
A14: 2350 | B14: 2450 | C14: 3.82 | D14: 1.32
A15: 2450 | B15: 2550 | C15: 4.62 | D15: 1.43
A16: 2550 | B16: 2650 | C16: 5.82 | D16: 2

Sheet ReqUnidades_BoyacaCasanare
A1: Demanda_MW_inf | B1: Demanda_MW_sup | C1: Boyaca-Casanare | D1: YOPALES (2,3,4 y 5) -Unidades Físicas
A2: 0 | B2: 291 | C2: 0 | D2: 0
A3: =+B2+1 -> 292 | B3: 301 | C3: 0.2 | D3: 0
A4: =+B3+1 -> 302 | B4: 316 | C4: 0.4 | D4: 0
A5: =+B4+1 -> 317 | B5: 336 | C5: 0.8 | D5: 0
A6: =+B5+1 -> 337 | B6: 351 | C6: 1.3 | D6: 0
A7: =+B6+1 -> 352 | B7: 361 | C7: 1.7 | D7: 0
A8: =+B7+1 -> 362 | B8: 381 | C8: 2.2 | D8: 1
A9: =+B8+1 -> 382 | B9: 401 | C9: 2.4 | D9: 1
A10: =+B9+1 -> 402 | B10: 426 | C10: 2.8 | D10: 1
A11: =+B10+1 -> 427 | B11: 445 | C11: 3.3 | D11: 1
A12: =+B11+1 -> 446 | B12: 465 | C12: 3.6 | D12: 1

Sheet ReqUnidades_NSantander
A1: Demanda_MW_inf | B1: Demanda_MW_sup | C1: Nsantander
A2: 0 | B2: 340 | C2: 0
A3: =+B2+1 -> 341 | B3: 360 | C3: 1
A4: 361 | B4: 380 | C4: 2

Sheet ReqUnidades_Antioquia
A1: Demanda_MW_inf | B1: Demanda_MW_sup | C1: Antioquia | D1: Demanda Mínima Unidades Físicas San Carlos
A2: 600 | B2: 699 | C2: 0 | D2: 4
A3: 700 | B3: 799 | C3: 0 | D3: 2
A4: 800 | B4: 1699 | C4: 0 | D4: 0
A5: 1700 | B5: 1749 | C5: 0 | D5: 0
A6: 1750 | B6: 1799 | C6: 0 | D6: 0

Sheet ReqUnidades_Oriental
A1: Demanda_MW_inf | B1: Demanda_MW_sup | C1: Oriental | D1: 1020-1120 | E1: 1120-1200 | F1: 1200-1320 | G1: Demanda Mínima - Unidades físicas San Carlos
A2: 1200 | B2: 1299 | C2: 3 | D2: 0 | E2: 0 | F2: 0 | G2: 0
A3: 1300 | B3: 1399 | C3: 1 | D3: 0 | E3: 0 | F3: 0 | G3: 0
A4: 1400 | B4: 1699 | C4: 0 | D4: 0 | E4: 0 | F4: 0 | G4: 0
A5: 1700 | B5: 1799 | C5: 0 | D5: 0 | E5: 0 | F5: 0 | G5: 0
A6: 1800 | B6: 1899 | C6: 0 | D6: 0 | E6: 0 | F6: 0 | G6: 0
A7: 1900 | B7: 1999 | C7: 0 | D7: 0 | E7: 0 | F7: 0 | G7: 0
A8: 2000 | B8: 2099 | C8: 0 | D8: 0 | E8: 0 | F8: 0 | G8: 0
A9: 2100 | B9: 2199 | C9: 0 | D9: 0 | E9: 0 | F9: 1 | G9: 0
A10: 2200 | B10: 2299 | C10: 0 | D10: 0 | E10: 1 | F10: 1 | G10: 0
A11: 2300 | B11: 2399 | C11: 0 | D11: 1 | E11: 1 | F11: 1 | G11: 0
A12: 2400 | B12: 2499 | C12: 1 | D12: 1 | E12: 1 | F12: 1 | G12: 0
A13: 2500 | B13: 2599 | C13: 2 | D13: 1 | E13: 1 | F13: 1 | G13: 0
... A20: 3200 | B20: 3299 | C20: 11.5 | D20: 1 | E20: 1 | F20: 2 | G20: 0

Sheet DemandaMínima
A1: Resumen consolidado de recomendación para demanda mínima
A3: Área Caribe
M4: Área Caribe
N5: En escenarios con demandas mínimas atípicas en Caribe 2 (en el rango entre 1500 y 1600 MW), las cuales pueden presentarse en festividades particulares como semana santa y fin de año, podría ser necesario el despacho de 2 unidades a 2.5 unidades equivalentes para control de tensión.
A21: Área Oriental
M23: Área Antioquia
N24: En escenarios con demandas mínimas atípicas en Antioquia (en el rango entre 700 y 800 MW), las cuales pueden presentarse en festividades particulares como semana santa, será necesario el despacho de por lo menos dos unidades físicas de San Carlos para control de tensión. De presentarse demandas entre 600 y 700 MW, dicho requerimiento de unidades pasará a ser de cuatro unidades físicas.
M33: Área Nordeste
N34: En escenarios con demandas mínimas atípicas en Nordeste (en el rango entre 750 y 850 MW, menor a 245 MW en Boyacá Casanare y menor a 175 MW en Norte de Santander), las cuales pueden presentarse en festividades particulares como semana santa, no se identifica la necesidad de requerimientos adicionales para control de tensión.
B40: En escenarios con demandas mínimas atípicas en Oriental (en el rango entre 1200 y 1400 MW), las cuales pueden presentarse en festividades particulares como semana santa, será necesario acompañar el requerimiento de unidades de Oriental con al menos dos unidades físicas de San Carlos, esto debido a que es la planta más efectiva en el control de potencia reactiva a través de la red 500 kV que ingresa al área.
A43: Área Suroccidental
M45: De otro lado, en caso de observar escenarios operativos dónde de acuerdo a al procedimiento establecido en la resolución CREG 025 del 1995 se requiera bajar tensión, pueden explorarse opciones de desconexión de líneas como las siguientes:

Sheet EquivUnid
A1: Area | B1: Planta | C1: Unidades por planta | D1: FKEYS | E1: Peso por unidad
A2: Antioquia | B2: Porce II | C2: 3 | D2: gPorceII-1 gPorceII-2 gPorceII-3 | E2: 2
A3: Antioquia | B3: Tasajera | C3: 3 | D3: gLatasa1 gLatasa2 gLatasa3 | E3: 1.64
A4: Antioquia | B4: Sierra Vapor | C4: 1 | D4: gSierraS1 | E4: 1.16
A5: Antioquia | B5: Jaguas | C5: 2 | D5: gJaguas-1 gJaguas-2 | E5: 0.96
A6: Antioquia | B6: Guadalupe III | C6: 6 | D6: gGuadaIII-1 gGuadaIII-2 gGuadaIII-3 gGuadaIII-4 gGuadaIII-5 gGuadaIII-6 | E6: 0.82
A7: Antioquia | B7: Guatapé | C7: 8 | D7: gGuatape1 gGuatape2 gGuatape3 gGuatape4 gGuatape5 gGuatape6 gGuatape7 gGuatape8 | E7: 0.77
A8: Antioquia | B8: Guadalupe IV | C8: 3 | D8: gGuadaIV1 gGuadaIV2 gGuadaIV3 | E8: 0.76
A9: Antioquia | B9: San Carlos | C9: 8 | D9: gSnCarlos1 gSnCarlos2 gSnCarlos3 gSnCarlos4 gSnCarlos5 gSnCarlos6 gSnCarlos7 gSnCarlos8 | E9: 0.76
A10: Antioquia | B10: Sierra Gas | C10: 2 | D10: gSierraG-1 gSierraG-2 | E10: 0.7
A11: Antioquia | B11: San Miguel | C11: 2 | D11: gSMigu-1 gSMigu-2 | E11: 0.64
A12: Antioquia | B12: Centro | C12: 3 | D12: gCentroG1 gCentroG2 gCentroS1 | E12: 0.55
A13: Antioquia | B13: Playas | C13: 3 | D13: gPlayas-1 gPlayas-2 gPlayas-3 | E13: 0.55
... A86: Boyaca-Casanare | B86: Villanueva | C86: 1 | D86: gbVill | E86: 0.7

Sheet Tensiones
A1: Area | B1: Barraje | C1: Substation.loc_name | D1: FKEYS | E1: Min_inf | F1: Min_sup | G1: Med_inf | H1: Med_sup | I1: Max_inf | J1: Max_sup
A2: Antioquia | B2: Ancón Sur EPM 230 kV | C2: Ancon EPM 220 | D2: NtpAEPM2 | E2: 227 | F2: 234 | G2: 223 | H2: 230 | I2: 226 | J2: 231
A3: Antioquia | B3: Barroso 110 kV | C3: Barroso 110 | D3: NtpBarr1 | E3: 111 | F3: 115 | G3: 108 | H3: 112 | I3: 110 | J3: 113
A4: Antioquia | B4: Central 115 kV | C4: Central 110 | D4: NtpCenl1 | E4: 111 | F4: 115 | G4: 108 | H4: 112 | I4: 110 | J4: 113
A5: Antioquia | B5: Certegui 110 kV | C5: Certegui 115 | D5: NtpCert1 | E5: 111 | F5: 117 | G5: 107 | H5: 115 | I5: 106 | J5: 115
A6: Antioquia | B6: Envigado 230 kV | C6: Envigado 220 | D6: NtpEnvi2 | E6: 228 | F6: 235 | G6: 224 | H6: 230 | I6: 226 | J6: 232
A7: Antioquia | B7: Guayabal 230 kV | C7: Guayabal 220 | D7: NtpGuay2 | E7: 226 | F7: 233 | G7: 222 | H7: 228 | I7: 224 | J7: 230
A8: Antioquia | B8: La Sierra 230 kV | C8: La Sierra 220 | D8: NtpLSie2 | E8: 232 | F8: 237 | G8: 233 | H8: 238 | I8: 234 | J8: 239
A9: Antioquia | B9: Playas 110 kV | C9: Playas 110 | D9: NtpPlay1 | E9: 113 | F9: 116 | G9: 113 | H9: 116 | I9: 113 | J9: 116
A10: Antioquia | B10: Primavera 230 kV | C10: Primavera 220 | D10: NtpPrim2 | E10: 234 | F10: 239 | G10: 233 | H10: 238 | I10: 234 | J10: 239
A11: Antioquia | B11: San Carlos 230 kV | C11: San Carlos 220 | D11: NtpSCar2 | E11: 228 | F11: 234 | G11: 231 | H11: 237 | I11: 231 | J11: 237
A12: Antioquia | B12: San Carlos 500 kV | C12: San Carlos 500 | D12: NtpSCar5 | E12: 495 | F12: 509 | G12: 498 | H12: 506 | I12: 499 | J12: 508
A13: Caribe | B13: Bolívar 220 kV | C13: Bolivar 220 | D13: NtpBoli2 | E13: 232 | F13: 238 | G13: 229 | H13: 233 | I13: 229 | J13: 232
... A62: Suroccidental | B62: Virginia 500 kV | C62: La Virginia 220 | D62: NtpVirg2 | E62: 499 | F62: 507 | G62: 498 | H62: 504 | I62: 500 | J62: 506

Sheet Info_Elems_Condiciones
A1: Area | B1: Medicion | C1: FKEYS | D1: Tipo
A2: Caribe2 | B2: Caribe2 | C2: "+LrtSabChn51r", "+LrtSabchn52r", "-LinOcaLom511", "+LinChnCop51T", "-LinBolTvj21" | D2: ForeignKey
A3: Oriental | B3: Primavera - Bacatá 500 kV + La Virginia - Nueva Esperanza 500 kV | C3: "-PmvBac500","+ExpLne0135" | D3: ForeignKey
A4: Boyaca-Casanare | B4: 1. YOPALES (2,3,4 y 5) | C4: "gYopal2","gNYopal3","gNYopal4","gNYopal5" | D4: ForeignKey

Sheet Graficas
A1: Área | B1: Subárea | C1: Restricciones en Alerta | D1: Restricciones en Emergencia | E1: Restricciones en estado Normal | F1: S/E Corto circuito > 99% | G1: Total Restricciones
A2: Antioquia | B2: Antioquia | C2: =COUNTIFS(Restricciones!$B:$B,Graficas!B2,Restricciones!$O:$O,0) -> 7 | D2: =COUNTIFS(Restricciones!$B:$B,Graficas!B2,Restricciones!$O:$O,1) -> 0 | E2: =COUNTIFS(Restricciones!$B:$B,Graficas!B2,Restricciones!$O:$O,3) -> 12 | F2: =COUNTIFS(Restricciones!$B:$B,Graficas!B2,Restricciones!$O:$O,2) -> 1 | G2: =+C2+D2+E2+F2 -> 20
A3: Caribe | B3: Atlántico | C3: =COUNTIFS(Restricciones!$B:$B,Graficas!B3,Restricciones!$O:$O,0) -> 6 | D3: =COUNTIFS(Restricciones!$B:$B,Graficas!B3,Restricciones!$O:$O,1) -> 3 | E3: =COUNTIFS(Restricciones!$B:$B,Graficas!B3,Restricciones!$O:$O,3) -> 9 | F3: =COUNTIFS(Restricciones!$B:$B,Graficas!B3,Restricciones!$O:$O,2) -> 13 | G3: =+C3+D3+E3+F3 -> 31
B4: Bolívar | C4: =COUNTIFS(Restricciones!$B:$B,Graficas!B4,Restricciones!$O:$O,0) -> 3 | D4: =COUNTIFS(Restricciones!$B:$B,Graficas!B4,Restricciones!$O:$O,1) -> 1 | E4: =COUNTIFS(Restricciones!$B:$B,Graficas!B4,Restricciones!$O:$O,3) -> 4 | F4: =COUNTIFS(Restricciones!$B:$B,Graficas!B4,Restricciones!$O:$O,2) -> 3 | G4: =+C4+D4+E4+F4 -> 11
B5: Cerromatoso | C5: =COUNTIFS(Restricciones!$B:$B,Graficas!B5,Restricciones!$O:$O,0) -> 3 | D5: =COUNTIFS(Restricciones!$B:$B,Graficas!B5,Restricciones!$O:$O,1) -> 0 | E5: =COUNTIFS(Restricciones!$B:$B,Graficas!B5,Restricciones!$O:$O,3) -> 0 | F5: =COUNTIFS(Restricciones!$B:$B,Graficas!B5,Restricciones!$O:$O,2) -> 1 | G5: =+C5+D5+E5+F5 -> 4
B6: Córdoba-Sucre | C6: =COUNTIFS(Restricciones!$B:$B,Graficas!B6,Restricciones!$O:$O,0) -> 11 | D6: =COUNTIFS(Restricciones!$B:$B,Graficas!B6,Restricciones!$O:$O,1) -> 7 | E6: =COUNTIFS(Restricciones!$B:$B,Graficas!B6,Restricciones!$O:$O,3) -> 3 | F6: =COUNTIFS(Restricciones!$B:$B,Graficas!B6,Restricciones!$O:$O,2) -> 1 | G6: =+C6+D6+E6+F6 -> 22
B7: GCM | C7: =COUNTIFS(Restricciones!$B:$B,Graficas!B7,Restricciones!$O:$O,0) -> 4 | D7: =COUNTIFS(Restricciones!$B:$B,Graficas!B7,Restricciones!$O:$O,1) -> 10 | E7: =COUNTIFS(Restricciones!$B:$B,Graficas!B7,Restricciones!$O:$O,3) -> 4 | F7: =COUNTIFS(Restricciones!$B:$B,Graficas!B7,Restricciones!$O:$O,2) -> 0 | G7: =+C7+D7+E7+F7 -> 18
A8: Nordeste | B8: Boyaca-Casanare | C8: =COUNTIFS(Restricciones!$B:$B,Graficas!B8,Restricciones!$O:$O,0) -> 0 | D8: =COUNTIFS(Restricciones!$B:$B,Graficas!B8,Restricciones!$O:$O,1) -> 0 | E8: =COUNTIFS(Restricciones!$B:$B,Graficas!B8,Restricciones!$O:$O,3) -> 10 | F8: =COUNTIFS(Restricciones!$B:$B,Graficas!B8,Restricciones!$O:$O,2) -> 0 | G8: =+C8+D8+E8+F8 -> 10
B9: Norte de Santander | C9: =COUNTIFS(Restricciones!$B:$B,Graficas!B9,Restricciones!$O:$O,0) -> 2 | D9: =COUNTIFS(Restricciones!$B:$B,Graficas!B9,Restricciones!$O:$O,1) -> 0 | E9: =COUNTIFS(Restricciones!$B:$B,Graficas!B9,Restricciones!$O:$O,3) -> 5 | F9: =COUNTIFS(Restricciones!$B:$B,Graficas!B9,Restricciones!$O:$O,2) -> 0 | G9: =+C9+D9+E9+F9 -> 7
B10: Santander | C10: =COUNTIFS(Restricciones!$B:$B,Graficas!B10,Restricciones!$O:$O,0) -> 0 | D10: =COUNTIFS(Restricciones!$B:$B,Graficas!B10,Restricciones!$O:$O,1) -> 0 | E10: =COUNTIFS(Restricciones!$B:$B,Graficas!B10,Restricciones!$O:$O,3) -> 1 | F10: =COUNTIFS(Restricciones!$B:$B,Graficas!B10,Restricciones!$O:$O,2) -> 0 | G10: =+C10+D10+E10+F10 -> 1
B11: Arauca | C11: =COUNTIFS(Restricciones!$B:$B,Graficas!B11,Restricciones!$O:$O,0) -> 0 | D11: =COUNTIFS(Restricciones!$B:$B,Graficas!B11,Restricciones!$O:$O,1) -> 0 | E11: =COUNTIFS(Restricciones!$B:$B,Graficas!B11,Restricciones!$O:$O,3) -> 0 | F11: =COUNTIFS(Restricciones!$B:$B,Graficas!B11,Restricciones!$O:$O,2) -> 0 | G11: =+C11+D11+E11+F11 -> 0
A12: Oriental | B12: Bogotá | C12: =COUNTIFS(Restricciones!$B:$B,Graficas!B12,Restricciones!$O:$O,0) -> 4 | D12: =COUNTIFS(Restricciones!$B:$B,Graficas!B12,Restricciones!$O:$O,1) -> 1 | E12: =COUNTIFS(Restricciones!$B:$B,Graficas!B12,Restricciones!$O:$O,3) -> 25 | F12: =COUNTIFS(Restricciones!$B:$B,Graficas!B12,Restricciones!$O:$O,2) -> 8 | G12: =+C12+D12+E12+F12 -> 38
B13: Meta | C13: =COUNTIFS(Restricciones!$B:$B,Graficas!B13,Restricciones!$O:$O,0) -> 5 | D13: =COUNTIFS(Restricciones!$B:$B,Graficas!B13,Restricciones!$O:$O,1) -> 1 | E13: =COUNTIFS(Restricciones!$B:$B,Graficas!B13,Restricciones!$O:$O,3) -> 2 | F13: =COUNTIFS(Restricciones!$B:$B,Graficas!B13,Restricciones!$O:$O,2) -> 0 | G13: =+C13+D13+E13+F13 -> 8
A14: Suroccidental | B14: Cauca-Nariño | C14: =COUNTIFS(Restricciones!$B:$B,Graficas!B14,Restricciones!$O:$O,0) -> 2 | D14: =COUNTIFS(Restricciones!$B:$B,Graficas!B14,Restricciones!$O:$O,1) -> 0 | E14: =COUNTIFS(Restricciones!$B:$B,Graficas!B14,Restricciones!$O:$O,3) -> 5 | F14: =COUNTIFS(Restricciones!$B:$B,Graficas!B14,Restricciones!$O:$O,2) -> 0 | G14: =+C14+D14+E14+F14 -> 7
B15: Valle | C15: =COUNTIFS(Restricciones!$B:$B,Graficas!B15,Restricciones!$O:$O,0) -> 0 | D15: =COUNTIFS(Restricciones!$B:$B,Graficas!B15,Restricciones!$O:$O,1) -> 0 | E15: =COUNTIFS(Restricciones!$B:$B,Graficas!B15,Restricciones!$O:$O,3) -> 8 | F15: =COUNTIFS(Restricciones!$B:$B,Graficas!B15,Restricciones!$O:$O,2) -> 0 | G15: =+C15+D15+E15+F15 -> 8
B16: Huila-Tolima | C16: =COUNTIFS(Restricciones!$B:$B,Graficas!B16,Restricciones!$O:$O,0) -> 0 | D16: =COUNTIFS(Restricciones!$B:$B,Graficas!B16,Restricciones!$O:$O,1) -> 0 | E16: =COUNTIFS(Restricciones!$B:$B,Graficas!B16,Restricciones!$O:$O,3) -> 3 | F16: =COUNTIFS(Restricciones!$B:$B,Graficas!B16,Restricciones!$O:$O,2) -> 0 | G16: =+C16+D16+E16+F16 -> 3
B17: Caquetá | C17: =COUNTIFS(Restricciones!$B:$B,Graficas!B17,Restricciones!$O:$O,0) -> 0 | D17: =COUNTIFS(Restricciones!$B:$B,Graficas!B17,Restricciones!$O:$O,1) -> 0 | E17: =COUNTIFS(Restricciones!$B:$B,Graficas!B17,Restricciones!$O:$O,3) -> 2 | F17: =COUNTIFS(Restricciones!$B:$B,Graficas!B17,Restricciones!$O:$O,2) -> 0 | G17: =+C17+D17+E17+F17 -> 2
B18: Suroccidente | C18: =COUNTIFS(Restricciones!$B:$B,Graficas!B18,Restricciones!$O:$O,0) -> 0 | D18: =COUNTIFS(Restricciones!$B:$B,Graficas!B18,Restricciones!$O:$O,1) -> 0 | E18: =COUNTIFS(Restricciones!$B:$B,Graficas!B18,Restricciones!$O:$O,3) -> 5 | F18: =COUNTIFS(Restricciones!$B:$B,Graficas!B18,Restricciones!$O:$O,2) -> 0 | G18: =+C18+D18+E18+F18 -> 5
A19: Total | C19: =+SUM(C2:C17) -> 47 | D19: =+SUM(D2:D17) -> 23 | E19: =+SUM(E2:E17) -> 93 | F19: =+SUM(F2:F17) -> 27 | G19: =+SUM(G2:G18) -> 195

Sheet RADIALIDADES
A1: Area | B1: Subarea | C1: Activo
A2: Antioquia | B2: Antioquia | C2: El Salto - Porce 110 kV | E2: Zona CANO
A3: Antioquia | B3: Antioquia | C3: Puerto Nare - Puerto Inmarco 110 kV
A4: Antioquia | B4: Antioquia | C4: Puerto Nare - Moriche 110 kV
A5: Antioquia | B5: Antioquia | C5: Cocorná - Teka 110 kV
A6: Antioquia | B6: Antioquia | C6: Cocorná - Puerto Boyacá 110 kV
A7: Antioquia | B7: Antioquia | C7: Puerto Boyacá - Vasconia 110 kV
A8: Antioquia | B8: Antioquia | C8: Palagua - Vasconia 110 kV
A9: Antioquia | B9: Antioquia | C9: Yarumal II - Yarumal 110 kV
A10: Antioquia | B10: Antioquia | C10: Hispania - THispania 1 110
A11: Antioquia | B11: Antioquia | C11: Cértegui - Itsmina 110 kV
A12: Antioquia | B12: Antioquia | C12: Caucheras - Chorodo 1 110
A13: Antioquia | B13: Antioquia | C13: Antioquia - Chorodo 1 110
A14: Antiquia | B14: Dispac | C14: Certegui - Itsmina 115 kV
... A112: Suroccidental | B112: Huila - Tolima | C112: Altamira - Segovianas 1 115

Sheet Bandas VQC
A1: NODO | B1: TIPO | C1: P | D1: Vmin | E1: Vmax
A2: CUESTECITAS 230 KV | B2: ORDINARIO | C2: 1 | D2: 225 | E2: 235
A3: CUESTECITAS 230 KV | B3: ORDINARIO | C3: 2 | D3: 225 | E3: 235
A4: CUESTECITAS 230 KV | B4: ORDINARIO | C4: 3 | D4: 225 | E4: 235
A5: CUESTECITAS 230 KV | B5: ORDINARIO | C5: 4 | D5: 225 | E5: 235
A6: CUESTECITAS 230 KV | B6: ORDINARIO | C6: 5 | D6: 226 | E6: 236
A7: CUESTECITAS 230 KV | B7: ORDINARIO | C7: 6 | D7: 226 | E7: 236
A8: CUESTECITAS 230 KV | B8: ORDINARIO | C8: 7 | D8: 226 | E8: 236
A9: CUESTECITAS 230 KV | B9: ORDINARIO | C9: 8 | D9: 228 | E9: 238
A10: CUESTECITAS 230 KV | B10: ORDINARIO | C10: 9 | D10: 228 | E10: 238
A11: CUESTECITAS 230 KV | B11: ORDINARIO | C11: 10 | D11: 228 | E11: 238
A12: CUESTECITAS 230 KV | B12: ORDINARIO | C12: 11 | D12: 228 | E12: 238
A13: CUESTECITAS 230 KV | B13: ORDINARIO | C13: 12 | D13: 228 | E13: 238
... A217: VIRGNIA 230 KV | B217: ORDINARIO | C217: 24 | D217: 229 | E217: 239
